{
  "fetchedAt": "2026-06-16T12:30:06.591Z",
  "stock": "000660",
  "source": "DART 정기공시 'IV. 이사의 경영진단 및 분석의견'",
  "periods": {
    "2026Q1": {
      "key": "2026Q1",
      "label": "2026 1분기",
      "reportName": "분기보고서 (2026.03)",
      "rcept_no": "20260515002287",
      "text": "이사의 경영진단 및 분석의견 \n 1. 예측정보에 대한 주의사항 \n ※ 기업공시서식 작성기준에 따라 분기보고서에는 본 항목을 기재하지 아니하였습니다. \n 2. 개요 \n ※ 기업공시서식 작성기준에 따라 분기보고서에는 본 항목을 기재하지 아니하였습니다. \n 3. 재무상태 및 영업실적 \n ※ 기업공시서식 작성기준에 따라 분기보고서에는 본 항목을 기재하지 아니하였습니다. \n 4. 유동성 및 자금조달과 지출 \n ※ 기업공시서식 작성기준에 따라 분기보고서에는 본 항목을 기재하지 아니하였습니다. \n 5. 부외거래 \n ※ 기업공시서식 작성기준에 따라 분기보고서에는 본 항목을 기재하지 아니하였습니다. \n 6. 그 밖에 투자의사결정에 필요한 사항 \n ※ 기업공시서식 작성기준에 따라 분기보고서에는 본 항목을 기재하지 아니하였습니다. \n V."
    },
    "2025Q4": {
      "key": "2025Q4",
      "label": "2025 4분기",
      "reportName": "사업보고서 (2025.12)",
      "rcept_no": "20260317000635",
      "text": "이사의 경영진단 및 분석의견 \n 1. 예측정보에 대한 주의사항 \n 본 사업보고서의 '이사의 경영진단 및 분석의견'은 당사의 사업 및 재무현황과 2025년도 영업실적에 대한 투자자의 전반적인 이해를 돕고자 하기와 같은 내용으로 구성하였으며, 본 '이사의 경영진단 및 분석의견' 항목에 포함된 모든 재무제표 및 관련된 분석 의견은 연결 기준으로 작성되었으니 참고하시기 바랍니다. \n 본 자료는 미래에 대한 예측정보를 포함하고 있습니다. 예측정보는 과거가 아닌 미래사건과 관계된 회사의 믿음ㆍ기대에 대한 진술이며, 향후 예상되는 회사의 경영현황 및 재무실적과 관련된 정보를 의미합니다. 그러한 예측정보는 위험과 불확실성, 그리고 회사의 실제 실적과 예측진술에 기재되거나 암시된 미래실적 간의 중대한 차이를 초래하는 다른 요인들을 내포하고 있습니다. \n 회사는 본 자료에 포함된 정보의 정확성과 완벽성에 대해서 암묵적으로든 또는 명시적으로든 보장할 수 없으며, 본 자료에 서술된 내용은 과거 또는 미래에 대한 약속이나 진술로 간주될 수 없습니다. 예측정보는 회사의 현재 계획, 추정 및 전망, 그리고 회사가 미래에 처하게 될 정치ㆍ경제적 환경에 근거하고 있으므로, 이용자들은 이러한 예측진술을 적정수준 이상으로 신뢰하여서는 안됩니다. \n 예측정보는 작성일 현재 시점에 기초하여 작성된 것이며, 당사는 동 예측정보 작성시점 이후에 발생하는 위험 또는 불확실성을 반영하기 위하여 예측정보에 기재한 사항을 수정하는 정정보고서를 공시할 의무는 없습니다. \n 2. 개요 \n 2025년 메모리 시장은 AI 기술의 전방위적 확산이 AI 메모리 수요 증가를 촉진하며 급격한 성장세를 보였습니다.당사는 업계 선두의 경쟁력을 갖춘 AI 메모리 제품의 판매를 대폭 확대하고 수익성 중심의 제품 운영 전략으로 시황 변화에 맞춰 적시에 투자를 진행한 결과, 2025년 연결 기준 매출은 97.1조원, 영업이익은 47.2조원을 기록하면서 매출과 영업이익 모두 2024년에 기록하였던 창사 이래 최대 실적을 경신하였습니다. \n [주요 경영지표] \n (단위: 백만원) \n 제78기 \n 제77기 \n 제76기 \n 매출액(A) \n 97,146,675 \n 66,192,960 \n 32,765,719 \n 영업이익(B) \n 47,206,319 \n 23,467,319 \n (7,730,313) \n 영업이익률(B/A) \n 48.6% \n 35.5% \n -23.6% \n 메모리 반도체 제조업은 끊임없는 기술 개발과 함께 양산 능력 확대를 통한 원가 경쟁력 강화가 필요한 산업이며, 이를 위해서는 대규모 투자가 필수적입니다. \n 최근 3년간 투자 추이를 살펴보면, 2023년은 수익성 확보를 위해 보수적 투자를 시행하여 연결 기준 유형자산 취득액 기준 6.6조원의 투자를 집행하였습니다. 2024년은 메모리 수요 증가에 대응하기 위한 투자가 증가하며 연결 기준 유형자산 취득액 기준 18.0조원의 투자를 집행하였습니다. 2025년은 수요 환경 지속 변화에 대응하기 위한 투자가 증가하며 연결 기준 유형자산 취득액 기준 30.2조원의 투자를 집행하였습니다. \n 2026년 메모리 시장은 미국의 보호무역, 상호관세와 중동 지정학적 리스크 심화 등으로 불확실성이 존재하나, AI 중심의 수요 확대와 기술 고도화에 힘입어 안정적인 성장세를 이어갈 것으로 전망됩니다. 특히, AI 추론 시장의 성장 및 Agentic AI, AI PC 확산으로 HBM을 비롯한 DRAM과 NAND 시장 모두 고성능/고용량으로 재편되고 있으며, 이러한 변화에 맞춰 업계 선두의 기술과 제품 경쟁력을 강화해 나갈 계획입니다. \n 3. 재무상태 및 영업실적 \n [요약 손익계산서] \n (단위: 백만원) \n 과목 \n 제78기 \n 제77기 \n 증감 \n I. 매출액 \n 97,146,675 \n 66,192,960 \n 30,953,715 \n II. 매출원가 \n 38,455,885 \n 34,364,814 \n 4,091,071 \n III. 매출총이익 \n 58,690,790 \n 31,828,146 \n 26,862,644 \n IV. 판매비와관리비 \n 11,484,471 \n 8,360,827 \n 3,123,644 \n V. 영업이익 \n 47,206,319 \n 23,467,319 \n 23,739,000 \n VI. 순영업외비용(이익) \n (3,259,233) \n (418,031) \n (2,841,202) \n VII. 법인세비용차감전순이익 \n 50,465,552 \n 23,885,350 \n 26,580,202 \n VIII. 법인세비용 \n 7,517,650 \n 4,088,448 \n 3,429,202 \n IX. 당기순이익 \n 42,947,902 \n 19,796,902 \n 23,151,000 \n ※ 상기 표의 재무정보는 주주총회 승인전 재무제표이며, 향후 정기주주총회에서 재무제표 승인 관련 안건이 부결되거나 수정이 발생한 경우 정정보고서를 통해 그 내용 및 사유 등을 반영할 예정입니다. \n 매출 제78기 당사 매출액은 97조 1,467억원으로 반도체 시황 개선에 따른 주요 제품 판가 상승 영향으로 전년 66조 1,930억원 대비 47% 증가하였습니다. 제품군별로는 전체 매출 중 DRAM과 NAND가 각각 77%와 21% 비중을 차지하였으며, 그 외 기타 매출은 2%를 차지하였습니다.\n 영업이익 \n 당기 영업이익은 47조 2,063억원으로 반도체 시황 개선에 따른 판가 상승 및 판매량 증가 영향으로 전기 대비 23조 7,390억 증가하였습니다. 당기 순영업외비용은 장기투자자산평가이익 등으로 전년 대비 2조 8,412억 감소하였으며, 법인세차감전순이익은 전기대비 26조 5,802억 증가한 50조 4,656억을 기록하였으며, 당기순이익은 전년 대비 23조 1,510억 증가한 42조 9,479억을 기록하였습니다. \n [요약 재무상태표] \n (단위: 백만원) \n 구분 \n 제78기 \n 제77기 \n 제76기 \n I. 유동자산 \n 69,458,073 \n 42,278,887 \n 30,468,100 \n ㆍ현금및현금성자산 \n 14,923,766 \n 11,205,117 \n 7,587,329 \n ㆍ단기금융상품 \n 14,679,719 \n 2,382,010 \n 472,617 \n ㆍ단기투자자산 \n 5,338,768 \n 569,236 \n 860,972 \n ㆍ매출채권 \n 18,199,078 \n 13,019,006 \n 6,600,273 \n ㆍ기타수취채권 \n 386,343 \n 293,061 \n 357,641 \n ㆍ재고자산 \n 14,289,390 \n 13,313,937 \n 13,480,659 \n ㆍ기타유동자산 \n 1,641,009 \n 1,496,520 \n 1,079,168 \n II. 비유동자산 \n 106,649,586 \n 77,576,322 \n 69,862,065 \n ㆍ관계기업 및 공동기업투자 \n 1,320,927 \n 1,940,663 \n 1,367,348 \n ㆍ장기투자자산 \n 14,547,099 \n 4,041,276 \n 4,105,704 \n ㆍ유형자산 \n 77,502,704 \n 60,157,474 \n 52,704,853 \n ㆍ무형자산 \n 4,049,402 \n 4,018,847 \n 3,834,567 \n ㆍ기타 \n 9,229,454 \n 7,418,062 \n 7,849,593 \n 자 산 총 계 \n 176,107,659 \n 119,855,209 \n 100,330,165 \n I. 유동부채 \n 37,378,999 \n 24,965,444 \n 21,007,810 \n II. 비유동부채 \n 18,061,909 \n 20,974,061 \n 25,818,603 \n 부 채 총 계 \n 55,440,908 \n 45,939,505 \n 46,826,413 \n I. 자본금 \n 3,657,652 \n 3,657,652 \n 3,657,652 \n II. 자본잉여금 \n 8,953,714 \n 4,487,123 \n 4,372,559 \n III. 기타자본 \n (1,348,598) \n (2,191,549) \n (2,269,294) \n IV. 기타포괄손익누계액 \n 2,676,862 \n 2,532,107 \n 1,014,055 \n V. 이익잉여금 \n 106,576,548 \n 65,418,061 \n 46,729,313 \n VI. 비지배지분 \n 150,573 \n 12,310 \n (533) \n 자 본 총 계 \n 120,666,751 \n 73,915,704 \n 53,503,752 \n 부 채 와 자 본 총 계 \n 176,107,659 \n 119,855,209 \n 100,330,165 \n ※ 상기 표의 재무정보는 주주총회 승인전 재무제표이며 향후 정기주주총회에서 재무제표 승인 관련 안건이 부결되거나 수정이 발생한 경우 정정보고서를 통해 그 내용 및 사유 등을 반영할 예정입니다. \n 자산 \n 당기말 자산 총액은 전기 대비 56조 2,525억원(46.9%) 증가한 176조 1,077억원입니다. 자산의 주요 증가 원인은 실적 개선에 따른 운용자금 증가로 단기금융상품 12조 2,977억 증가 및 단기투자자산 4조 7,695억원 증가, 투자 집행 증가에 따른 유형자산 17조 3,452억 증가, 공정가치평가이익 발생에 따른 장기투자자산 10조 5,058억원 증가 영향입니다. \n 부채 \n 당기말 부채 총액은 전기대비 9조 5,014억(20.7%) 증가한 55조 4,409억원입니다. 유동부채가 12조 4,136억(49.7%) 증가하였고, 비유동부채가 2조 9,122억(13.9%) 감소하였습니다. 부채의 주요 변동 원인으로는 미지급비용 2조 3,001억 증가, 미지급법인세 3조 9,399억 증가 및 교환사채 교환권 평가 등에 따른 내재파생상품부채 3조 1,727억 증가한 영향입니다. \n 자본 \n 당기말 자본 총액은 전기 대비 46조 7,510억(63.2%) 증가한 120조 6,668억원으로, 주요 증가 원인은 시황 개선에 따른 당기순이익 42조 9,479억 발생 및 자기주식 처분에 따른 자본잉여금 4조 3,131억원 증가한 영향입니다. \n 신규 및 중단 사업 해당사항 없습니다.\n 경영합리화 관련 해당사항 없습니다.\n 환율 변동 영향 외환위험은 미래예상거래, 인식된 자산과 부채 및 해외사업장에 대한 순투자가 기능통화 외의 통화로 표시될 때 발생합니다. 당사는 영업 측면에서 매출의 대부분이 환율 변동 위험에 노출되어 있고, 생산을 위한 원부자재와 투자 관련 지출의 상당 비중이 환율 변동에 영향을 받고 있습니다. 이에 당사는 외화표시 자산 및 부채에 대해 환율변동에 의한 리스크를 최소화하여 재무구조의 건전성 및 경영 안정성 제고를 목표로 환 리스크 관리에 만전을 기하고 있습니다.\n 당기말 현재 연결회사의 화폐성 외화자산 및 외화부채의 내역은 다음과 같습니다. \n (원화단위: 백만원, 외화단위: 외화 백만단위) \n 구분 \n 자산 \n 부채 \n 현지통화 \n 원화환산 \n 현지통화 \n 원화환산 \n USD \n 23,074 \n 33,108,951 \n 15,528 \n 22,280,863 \n JPY \n 904 \n 8,295 \n 116,044 \n 1,064,852 \n CNY \n 1,748 \n 357,939 \n 2,734 \n 559,886 \n EUR \n 25 \n 42,240 \n 149 \n 251,626 \n 또한, 연결회사는 외화사채 및 차입금의 환위험을 회피하기 위하여 연결재무제표 주석 21에서 설명하는 바와 같이 통화스왑계약 및 통화이자율스왑계약을 체결하고 있습니다. \n 당기말 현재 각 외화에 대한 기능통화의 환율이 10% 변동시, 동 환율변동이 법인세비용차감전순이익에 미치는 영향은 다음과 같습니다. \n (단위: 백만원) \n 구 분 \n 10% 상승시 \n 10% 하락시 \n USD \n 1,210,371 \n (1,210,371) \n JPY \n (105,656) \n 105,656 \n CNY \n (20,195) \n 20,195 \n EUR \n (20,939) \n 20,939 \n 자산손상 또는 감액손실 \n 종업원급여에서 발생한 자산, 재고자산, 이연법인세자산을 제외한 모든 비금융자산에 대해서는 매 보고기간말마다 자산손상을 시사하는 징후가 있는지를 검토하며, 만약 그러한 징후가 있다면 당해 자산의 회수가능액을 추정하고 있습니다. 단, 사업결합으로 취득한 영업권 및 내용연수가 비한정인 무형자산, 아직 사용할 수 없는 무형자산에 대해서는 자산손상을 시사하는 징후와 관계없이 매년 회수가능액과 장부금액을 비교하여 손상검사를 하고 있습니다. \n 회수가능액은 개별 자산별로, 또는 개별 자산의 회수가능액을 추정할 수 없다면 그 자산이 속하는 현금창출단위별로 회수가능액을 추정하고 있습니다. 회수가능액은 사용가치와 순공정가치 중 큰 금액으로 결정하고 있습니다. 사용가치는 자산이나 현금창출단위에서 창출될 것으로 기대되는 미래현금흐름을 화폐의 시간가치 및 미래현금흐름을 추정할 때 조정되지 아니한 자산의 특유위험에 대한 현행 시장의 평가를 반영한 적절한 할인율로 할인하여 추정합니다.연결회사는 당기 중 계정과목별 손상차손 금액으로 유형자산 총 45,157백만원 손상, 무형자산 총 38,053백만원 손상 등을 인식하였습니다. \n 당사의 자산손상에 대한 구체적인 내용은 'Ⅲ. 재무에 관한 사항' - '3. 연결재무제표 주석'을 참고하시기 바랍니다. \n 4. 유동성 및 자금조달과 지출 \n 당기말 현재 회사가 보유 중인 현금및현금성자산 합계(*) 는 34조 9,423억원으로 전기말 14조 1,564억원 대비 20조 7,859억원 증가하였습니다. 전기말 8조 5,274억원의 순차입금에서 당기 말 12조 6,943억원의 순현금으로 전환하였습니다. \n (*) 현금 및 현금성 자산 합계 = 현금및현금성자산 + 단기금융상품 + 단기투자자산 \n [순현금(순차입금) 변동내역] \n (단위: 백만원) \n 제78기 \n 제77기 \n 제76기 \n 현금및현금성자산 \n 14,923,766 \n 11,205,117 \n 7,587,329 \n 단기금융상품 및 단기투자자산 \n 20,018,487 \n 2,951,246 \n 1,333,589 \n 현금및현금성자산 합계 \n 34,942,253 \n 14,156,363 \n 8,920,918 \n 차입금(유동) \n 8,161,757 \n 5,252,238 \n 9,857,189 \n 차입금(비유동) \n 14,086,148 \n 17,431,495 \n 19,611,443 \n 차입금 합계 \n 22,247,905 \n 22,683,733 \n 29,468,632 \n 순현금(순차입금) \n 12,694,348 \n (8,527,370) \n (20,547,714) \n 개별 기업의 단기적인 유동성의 건전성 수준을 가늠해 볼 수 있는 대표적인 재무비율은 유동비율과 당좌비율이 있으며, 2025년말 기준 당사의 해당 재무비율 현황은 하기와 같습니다. \n [당사 유동성 비율 추이] \n (단위: 백만원) \n 제78기 \n 제77기 \n 제76기 \n 유동비율(= ① / ②) \n 1.9배 \n 1.7배 \n 1.5배 \n ①유동자산 \n 69,458,073 \n 42,278,887 \n 30,468,100 \n ②유동부채 \n 37,379,017 \n 24,965,444 \n 21,007,810 \n 당좌비율(= (① + ②) / ③) \n 1.4배 \n 1.1배 \n 0.7배 \n ①현금및현금성자산 총액(*) \n 34,942,253 \n 14,156,363 \n 8,920,918 \n ②매출채권 \n 18,199,078 \n 13,019,006 \n 6,600,273 \n ③유동부채 \n 37,379,017 \n 24,965,444 \n 21,007,810 \n ※ 현금및현금성자산 총액 = 현금및현금성자산 + 단기금융상품 + 단기투자자산 \n 최근 3년간 당사의 유동비율은 1.5배 ~ 1.9배, 당좌비율은 0.7배 ~ 1.4배로 적정 수준의 유동성을 유지하고 있으며 회사의 우수한 대외 신인도에 기반한 외부자금 조달능력 등을 감안할 때, 향후 1년 기간내 회사의 유동성 위험이 발생할 가능성은 낮을 것으로 판단하고 있습니다. \n [당사 대외 신용등급 현황] \n 구분 \n 제78기말 \n 제77기말 \n 국내 \n 한국기업평가 \n AA+ \n AA \n 한국신용평가 \n AA+ \n AA \n NICE신용평가 \n AA+ \n AA \n 해외 \n Moody's \n Baa1 \n Baa2 \n S&P \n BBB+ \n BBB \n Fitch \n BBB \n BBB \n ※ 한국기업평가와 S&P 신용등급은 보고서 제출일 현재 기준으로 작성하였습니다. \n ※ 한국기업평가는 2026년 1월 29일 기준 AA에서 AA+로, NICE신용평가는 2026년 3월 11일 기준으로 AA에서 AA+로, 한국신용평가는 2026년 3월 11일 기준으로 AA에서 AA+로 평가등급이 변경되었습니다.※ S&P는 2026년 2월 5일 기준 BBB에서 BBB+로 평가등급이 변경되었습니다. \n 당사는 여유있는 유동성이 확보될 수 있도록 적절한 만기나 충분한 유동성을 제공해주는 정기예금, 수시입출금식 예금 등의 금융상품을 선택하여 잉여자금을 투자하고 있습니다. \n 2025년말 기준 회사와 종속기업이 보유하고 있는 전체 현금 및 현금성 자산 중 만기 3개월 이내의 현금 및 현금성 자산은 14조 9,238억원, 만기 1년 이내의 단기금융상품과 단기투자자산은 각각 13조 2,723억원, 6조 7,462억원이며, 사용이 제한되어 있는 금융상품은 중소기업 지원을 위한 은행예금 2,225억원(상생펀드) 등 총 2,312억원입니다. (연결재무제표 주석 '7. 사용제한 금융상품' 참조) \n 차입금 현황 \n (1) 차입금 잔액의 변동당사는 2025년 중 주요 금융기관 등으로부터 8조 1,837억원을 신규로 조달하였으며, 회사채 및 금융기관차입금의 만기도래로 7조 4,161억원을 상환하였습니다. 2025년말 당사의 연결 기준 차입금 잔액은 교환사채의 주식 교환 및 환율 증가 영향 등으로 전기말 22조 6,837억원 대비 약 4,358억원 감소하였습니다. \n (단위: 백만원) \n 제78기말 \n 제77기말 \n 증감(*) \n 금융기관차입금 \n 6,745,848 \n 7,448,815 \n (702,967) \n 회사채 \n 15,502,057 \n 15,234,918 \n 267,139 \n 기타 \n 0 \n 0 \n - \n 계 \n 22,247,905 \n 22,683,733 \n (435,828) \n 가중평균차입이자율 \n 3.96% \n 3.99% \n - \n (*) 차입금의 증감에는 외화차입금에 대한 외화환산손익이 포함되어 있습니다. \n (2) 만기도래 현황 \n 당사는 만기 기간별 분류에 기반한 유동성 전략 및 계획을 통하여 유동성 위험을 관리하고 있습니다. 당기말 현재 연결실체가 보유한 금융부채의 계약상 만기는 다음과 같으며, 이러한 금융부채의 조기상환의무는 없습니다. \n (단위: 백만원) \n 1년 이하 \n 1년에서 2년 이하 \n 2년에서 5년 이하 \n 5년 초과 \n 합계 \n 금융기관차입금 \n 3,982,722 \n 2,103,976 \n 888,493 \n 0 \n 6,975,192 \n 회사채 \n 3,996,104 \n 2,741,584 \n 7,787,797 \n 3,272,460 \n 17,797,944 \n 계 \n 7,978,826 \n 4,845,560 \n 8,676,290 \n 3,272,460 \n 24,773,136 \n 만기비중 \n 32% \n 20% \n 35% \n 13% \n 100% \n ※ 금융부채의 만기에는 차입금에 대한 이자가 포함되어 있습니다. \n (3) 조달자금과 관련된 이행조건 여부당사가 발행한 공모 사채에는 투자자 보호를 위한 재무비율 유지, 담보권 설정제한, 자산처분액 제한 등의 의무조건이 부과되어 있으며, 당사는 이와 같은 의무조건을 준수하고 있습니다. \n 리스 현황 \n 당사의 당기말 현재 리스부채와 관련된 미래 지급할 각 기간별 최소리스료의 총합계와 현재가치, 유동성 구분 내역은 다음과 같습니다. \n (단위: 백만원) \n 구분 \n 리스료지급액 \n 1년이내 \n 576,548 \n 1년초과 ~ 5년이내 \n 1,494,878 \n 5년초과 \n 944,492 \n 12월 31일 현재 할인되지 않은 리스부채 \n 3,015,918 \n 12월 31일 현재 연결재무상태표에 인식된 리스부채 \n 2,509,943 \n 유동 리스부채 \n 547,296 \n 비유동 리스부채 \n 1,962,647 \n 자금 지출 관련 \n 당사는 2020년 인텔의 Non-Volatile Memory Solutions Group의 옵테인 사업부를 제외한 NAND 사업부문 전체를 인수하는 영업양수도 계약을 체결하였으며, 2025년 3월, NAND 사업부문 인수 절차를 최종 완료하였습니다.※ 상기 영업양수도에 관한 상세한 내용은 2025년 3월 28일 정정공시된 ' \n 주요사항보고서(영업양수결정) \n '를 참고하시기 바랍니다. \n 5. 부외거래 \n 연결회사와 관련하여 계류 중인 중요한 소송사건 및 클레임은 중국 반독점법 위반여부에 대한 조사가 있습니다. 당기말 현재 당사는 동 조사의 최종결과를 예측할 수 없습니다.당기말 현재 회사는 상기 소송 외에 지적재산권 등과 관련하여 여러 분쟁에 대응하고있으며, 과거 사건에 의한 현재 의무이고 향후 자원의 유출가능성이 높으며 손실금액을 신뢰성 있게 추정할 수 있는 경우 동 금액을 부채로 인식하고 있습니다.당사의 부외거래에 관한 자세한 내용은 'Ⅲ. 재무에 관한 사항' - '3. 연결재무제표 주석' 및 '5. 재무제표 주석' 내 '우발부채와 약정사항'을 참고하시기 바랍니다. \n 6. 그 밖에 투자의사결정에 필요한 사항 \n 중요한 회계정책 및 추정에 관한 사항 \n 연결회사는 2025년 1월 1일로 개시하는 회계기간부터 다음의 제ㆍ개정 기준서 및 해석서를 신규로 적용하였습니다. \n (1) 기업회계기준서 제1021호 '환율변동효과'와 기업회계기준서 제1101호 '한국채택국제회계기준의 최초채택' 개정 - 교환가능성 결여 \n 통화의 교환가능성을 평가하고 다른 통화와 교환이 가능하지 않다면 현물환율을 추정하며 관련 정보를 공시하도록 하고 있습니다. 해당 기준서의 개정이 연결재무제표에 미치는 중요한 영향은 없습니다. \n (2) 기업회계기준서 제1117호 '보험계약' 개정 \n 보험계약을 측정하기 위해 사용한 투입변수의 추정기법이 보험 관련 법규에서 요구하는 원칙적인 추정기법과 다른 경우, 그 차이내역과 재무제표에 미치는 영향이 재무제표이용자들에게 목적적합하고 중요하다고 판단된다면 이를 공시합니다. \n 당사의 중요한 회계정책 및 추정에 관한 사항은 'III. 재무에 관한 사항' - '3. 연결재무제표 주석' - '2. 중요한 회계정책 '을 참고하시기 바랍니다. \n 환경 및 종업원 등에 관한 사항 \n 당사의 환경관련 제재 및 이행현황 등에 관한 사항은 'XI. 그밖에 투자자 보호를 위하여 필요한 사항' - '3. 제재 등과 관련된 사항'을 참고하시기 바랍니다.종업원과 관련하여 주요 핵심인력 이동 등 회사 인력의 중요한 변동은 없었으며, 종업원 현황 등 종업원과 관련된 구체적인 사항은 'Ⅷ. 임원 및 직원 등에 관한 사항'을 참고하시기 바랍니다.\n 법규상의 규제에 관한 사항 \n 당사가 영위하는 사업과 관련된 법규상 주요 규제내용에 관한 사항은 'Ⅱ. 사업의 내용' - '7. 기타 참고사항' - '마. 정부나 지방자치단체의 법률 규정 등에 의한 규제사항'을 참고하시기 바랍니다. \n 파생상품 및 위험관리정책에 관한 사항 \n 당사의 주요 파생상품 및 위험관리정책은 'II. 사업의 내용' - '5. 위험관리 및 파생거래' 및 'Ⅲ. 재무에 관한 사항' - '3. 연결재무제표 주석'을 참고하시기 바랍니다. \n V."
    },
    "2024Q4": {
      "key": "2024Q4",
      "label": "2024 4분기",
      "reportName": "사업보고서 (2024.12)",
      "rcept_no": "20250319000665",
      "text": "이사의 경영진단 및 분석의견 \n 예측정보에 대한 주의사항 본 사업보고서의 '이사의 경영진단 및 분석의견'은 당사의 사업 및 재무현황과 2024년도 영업실적에 대한 투자자의 전반적인 이해를 돕고자 하기와 같은 내용으로 구성하였으며, 본 '이사의 경영진단 및 분석의견' 항목에 포함된 모든 재무제표 및 관련된 분석 의견은 연결 기준으로 작성되었으니 참고하시기 바랍니다. 1. 개요 2. 재무상태 및 영업실적 3. 유동성 관리정책 및 현황 4. 부외거래 5. 그 밖에 투자의사결정에 필요한 사항\n 본 자료는 미래에 대한 예측정보를 포함하고 있습니다. 예측정보는 과거가 아닌 미래사건과 관계된 회사의 믿음ㆍ기대에 대한 진술이며, 향후 예상되는 회사의 경영현황 및 재무실적과 관련된 정보를 의미합니다. 그러한 예측정보는 위험과 불확실성, 그리고 회사의 실제 실적과 예측진술에 기재되거나 암시된 미래실적 간의 중대한 차이를 초래하는 다른 요인들을 내포하고 있습니다. \n 회사는 본 자료에 포함된 정보의 정확성과 완벽성에 대해서 암묵적으로든 또는 명시적으로든 보장할 수 없으며, 본 자료에 서술된 내용은 과거 또는 미래에 대한 약속이나 진술로 간주될 수 없습니다. 예측정보는 회사의 현재 계획, 추정 및 전망, 그리고 회사가 미래에 처하게 될 정치ㆍ경제적 환경에 근거하고 있으므로, 이용자들은 이러한 예측진술을 적정수준 이상으로 신뢰하여서는 안됩니다. \n 예측정보는 작성일 현재 시점에 기초하여 작성된 것이며, 당사는 동 예측정보 작성시점 이후에 발생하는 위험 또는 불확실성을 반영하기 위하여 예측정보에 기재한 사항을 수정하는 정정보고서를 공시할 의무는 없습니다. \n 1. 개요 \n 2024년 메모리 시장은 AI향 서버와 클라우드 컴퓨팅 등 첨단 기술의 발전으로 고성능 메모리 수요 증가와 HBM 및 DDR5 등 신규 메모리 기술 도입 등으로 전반적인 반도체 업황 개선에 힘입어 당사는 두드러진 성장세를 보였습니다.업계 선두의 AI 메모리 기술력과 수익성 중심의 사업 운영, 시황 변화에 따른 적기 투자 진행으로 연결 기준 매출은 66.2조원으로 전년 대비 33.4조원 증가하였으며, 영업이익 또한 23.5조원으로 흑자 전환하면서 매출과 영업이익 모두 창사 이래 최대의 실적을 기록하는 성과를 달성하였습니다. \n [주요 경영지표] \n (단위: 백만원) \n 제77기 \n 제76기 \n 제75기 \n 매출액(A) \n 66,192,960 \n 32,765,719 \n 44,621,568 \n 영업이익(B) \n 23,467,319 \n (7,730,313) \n 6,809,417 \n 영업이익률(B/A) \n 35.5% \n -23.6% \n 15.3% \n 메모리 반도체 제조업은 끊임없는 기술 개발과 함께 양산 능력 확대를 통한 원가 경쟁력 강화가 필요한 산업이며, 이를 위해서는 대규모 투자가 필수적입니다. \n 최근 3년간 투자 추이를 살펴보면, 2022년은 장비와 인프라 확보 등을 위한 투자가 증가하며 연결 기준 유형자산 취득액 기준 19.6조원의 투자를 집행하였습니다 \n . \n 2023년은 수익성 확보를 위해 보수적 투자를 시행하여 연결 기준 유형자산 취득액 기준 6.6조원의 투자를 집행하였습니다. 2024년은 메모리 수요 증가에 대응하기 위한 투자가 증가하며 연결 기준 유형자산 취득액 기준 18.0조원의 투자를 집행하였습니다. \n 2025년 메모리 시장은 PC 및 스마트폰 업체들의 재고 조정이 진행되고 보호무역주의 강화와 지정학적 리스크 심화 등으로 수요 불확실성이 존재하나, Set 전반에 걸친 수요 개선과 컨슈머 제품의 재고 조정이 마무리되면서 수급 상황은 점차 개선될 것으로 전망됩니다. 앞으로 다가올 온디바이스 AI 수요에 대비하여 데이터 처리 속도와 전력 효율을 개선한 다양한 제품군도 준비 중이며, 고객 수요가 확대되는 시기에 맞춰 적기 공급함으로써 HBM 시장에서 리더십을 계속 이어 나갈 계획입니다. \n 2. 재무상태 및 영업실적 \n [요약 손익계산서] \n (단위: 백만원) \n 과목 \n 제77기 \n 제76기 \n 증감 \n I. 매출액 \n 66,192,960 \n 32,765,719 \n 33,427,241 \n II. 매출원가 \n 34,364,814 \n 33,299,167 \n 1,065,647 \n III. 매출총이익 \n 31,828,146 \n (533,448) \n 32,361,594 \n IV. 판매비와관리비 \n 8,360,827 \n 7,196,865 \n 1,163,962 \n V. 영업이익 \n 23,467,319 \n (7,730,313) \n 31,197,632 \n VI. 순영업외비용(이익) \n (418,031) \n 3,927,503 \n (4,345,534) \n VII. 법인세비용차감전순이익 \n 23,885,350 \n (11,657,816) \n 35,543,166 \n VIII. 법인세비용(수익) \n 4,088,448 \n (2,520,269) \n 6,608,717 \n IX. 당기순이익(손실) \n 19,796,902 \n (9,137,547) \n 28,934,449 \n ※ 상기 표의 재무정보는 주주총회 승인전 재무제표이며, 향후 정기주주총회에서 재무제표 승인 관련 안건이 부결되거나 수정이 발생한 경우 정정보고서를 통해 그 내용 및 사유 등을 반영할 예정입니다. \n 매출 제77기 당사 매출액은 66조 1,930억원으로 반도체 시황 개선에 따른 주요 제품 판가 상승 영향으로 전년 32조 7,657억원 대비 102% 증가하였습니다. 제품군별로는 전체 매출 중 DRAM과 NAND가 각각 68%와 29% 비중을 차지하였으며, 그 외 기타 매출은 3%를 차지하였습니다.\n 영업이익 \n 당기 영업이익은 23조 4,673억원으로 반도체 시황 개선에 따른 판가 상승 및 판매량 증가 영향으로 전기 대비 31조 1,976억 증가, 흑자전환하였습니다. 당기 순영업외비용은 전기 장기투자자산평가손실 및 파생상품손실 기저효과로 전년 대비 4조 3,455억 감소하였으며, 법인세차감전순이익은 전기대비 35조 5,432억 증가한 23조 8,854억을 기록(흑자전환)하였으며, 당기순이익은 전년 대비 28조 9,344억 증가한 19조 7,969억을 기록(흑자전환)하였습니다. \n [요약 재무상태표] \n (단위: 백만원) \n 구분 \n 제77기 \n 제76기 \n 제75기 \n I. 유동자산 \n 42,278,887 \n 30,468,100 \n 28,733,332 \n ㆍ현금및현금성자산 \n 11,205,117 \n 7,587,329 \n 4,977,007 \n ㆍ단기금융상품 \n 2,382,010 \n 472,617 \n 415,625 \n ㆍ단기투자자산 \n 569,236 \n 860,972 \n 1,016,360 \n ㆍ매출채권 \n 13,019,006 \n 6,600,273 \n 5,186,054 \n ㆍ기타수취채권 \n 293,061 \n 357,641 \n 272,512 \n ㆍ재고자산 \n 13,313,937 \n 13,480,659 \n 15,664,707 \n ㆍ기타유동자산 \n 1,496,520 \n 1,079,168 \n 1,201,067 \n II. 비유동자산 \n 77,576,322 \n 69,862,065 \n 75,138,180 \n ㆍ관계기업 및 공동기업투자 \n 1,940,663 \n 1,367,348 \n 1,352,845 \n ㆍ장기투자자산 \n 4,041,276 \n 4,105,704 \n 5,733,544 \n ㆍ유형자산 \n 60,157,474 \n 52,704,853 \n 60,228,528 \n ㆍ무형자산 \n 4,018,847 \n 3,834,567 \n 3,512,107 \n ㆍ기타비유동자산 \n 7,418,062 \n 7,849,593 \n 4,311,156 \n 자 산 총 계 \n 119,855,209 \n 100,330,165 \n 103,871,512 \n I. 유동부채 \n 24,965,444 \n 21,007,810 \n 19,843,696 \n II. 비유동부채 \n 20,974,061 \n 25,818,603 \n 20,737,274 \n 부 채 총 계 \n 45,939,505 \n 46,826,413 \n 40,580,970 \n I. 자본금 \n 3,657,652 \n 3,657,652 \n 3,657,652 \n II. 자본잉여금 \n 4,487,123 \n 4,372,559 \n 4,336,170 \n III. 기타자본 \n (2,191,549) \n (2,269,294) \n (2,311,409) \n IV. 기타포괄손익누계액 \n 2,532,107 \n 1,014,055 \n 898,682 \n V. 이익잉여금 \n 65,418,061 \n 46,729,313 \n 56,685,260 \n VI. 비지배지분 \n 12,310 \n (533) \n 24,187 \n 자 본 총 계 \n 73,915,704 \n 53,503,752 \n 63,290,542 \n 부 채 와 자 본 총 계 \n 119,855,209 \n 100,330,165 \n 103,871,512 \n ※ 상기 표의 재무정보는 주주총회 승인전 재무제표이며 향후 정기주주총회에서 재무제표 승인 관련 안건이 부결되거나 수정이 발생한 경우 정정보고서를 통해 그 내용 및 사유 등을 반영할 예정입니다. \n 자산 \n 당기말 자산 총액은 전기 대비 19조 5,250억원(19.5%) 증가한 119조 8,552억원입니다. 자산의 주요 증가 원인은 매출채권 6조 4,187억 증가 및 투자 집행 증가에 따른 유형자산 7조 4,526억 증가 영향입니다.\n 부채 \n 당기말 부채 총액은 전기대비 8,869억(1.9%) 감소한 45조 9,395억원입니다. 유동부채가 3조 9,576억(18.8%) 증가하였고, 비유동부채가 4조 8,445억(18.8%) 감소하였습니다. 부채의 주요 변동 원인으로는 차입금 상환 증가로 총차입금이 6조 7,849억 감소하였으며, 미지급금이 3조 6,737억, 미지급법인세가 3조 400억 증가한 영향입니다. \n 자본 \n 당기말 자본 총액은 전기 대비 20조 4,120억(38.2%) 증가한 73조 9,157억원으로 주요 증가 원인은 시황 개선에 따른 당기순이익 19조 7,969억 발생 및 배당금지급 8,263억원 등입니다. \n 신규 및 중단 사업 해당사항 없습니다.\n 경영합리화 관련 해당사항 없습니다.\n 환율 변동 영향 외환위험은 미래예상거래, 인식된 자산과 부채 및 해외사업장에 대한 순투자가 기능통화 외의 통화로 표시될 때 발생합니다. 당사는 영업 측면에서 매출의 대부분이 환율 변동 위험에 노출되어 있고, 생산을 위한 원부자재와 투자 관련 지출의 상당 비중이 환율 변동에 영향을 받고 있습니다. 이에 당사는 외화표시 자산 및 부채에 대해 환율변동에 의한 리스크를 최소화하여 재무구조의 건전성 및 경영 안정성 제고를 목표로 환 리스크 관리에 만전을 기하고 있습니다.\n 당기말 현재 연결회사의 화폐성 외화자산 및 외화부채의 내역은 다음과 같습니다. \n (원화단위: 백만원, 외화단위: 외화 백만단위) \n 구분 \n 자산 \n 부채 \n 현지통화 \n 원화환산 \n 현지통화 \n 원화환산 \n USD \n 19,847 \n 29,175,111 \n 15,530 \n 22,829,784 \n JPY \n 514 \n 4,817 \n 116,986 \n 1,095,553 \n CNY \n 1,282 \n 257,983 \n 1,715 \n 345,224 \n EUR \n 14 \n 20,916 \n 399 \n 609,451 \n 또한, 연결회사는 외화사채 및 차입금의 환위험을 회피하기 위하여 연결재무제표 주석 21에서 설명하는 바와 같이 통화스왑계약 및 통화이자율스왑계약을 체결하고 있습니다. \n 당기말 현재 각 외화에 대한 기능통화의 환율이 10% 변동시, 동 환율변동이 법인세비용차감전순이익에 미치는 영향은 다음과 같습니다. \n (단위: 백만원) \n 구 분 \n 10% 상승시 \n 10% 하락시 \n USD \n 781,121 \n (781,121) \n JPY \n (109,074) \n 109,074 \n CNY \n (8,724) \n 8,724 \n EUR \n (58,854) \n 58,854 \n 자산손상 또는 감액손실 \n 당사는 종업원급여에서 발생한 자산, 재고자산, 이연법인세자산을 제외한 모든 비금융자산에 대해서는 매 보고기간말마다 자산손상을 시사하는 징후가 있는지를 검토하며, 만약 그러한 징후가 있다면 당해 자산의 회수가능액을 추정하고 있습니다. 단, 사업결합으로 취득한 영업권 및 내용연수가 비한정인 무형자산, 아직 사용할 수 없는 무형자산에 대해서는 자산손상을 시사하는 징후와 관계없이 매년 회수가능액과 장부금액을 비교하여 손상검사를 하고 있습니다. 회수가능액은 개별 자산별로, 또는 개별 자산의 회수가능액을 추정할 수 없다면 그 자산이 속하는 현금창출단위별로 회수가능액을 추정하고 있으며, 회수가능액은 사용가치와 순공정가치 중 큰 금액으로 결정하고 있습니다.\n 연결회사는 당기 중 계정과목별 손상차손(환입)금액으로 유형자산 총 9백만원 환입, 무형자산 총 216백만원 손상 등을 인식하였습니다. \n 당사의 자산손상에 대한 구체적인 내용은 'Ⅲ. 재무에 관한 사항' - '3. 연결재무제표 주석'을 참고하시기 바랍니다.\n 3. 유동성 관리정책 및 현황 \n 당기말 현재 회사가 보유 중인 현금 및 현금성 자산 합계(*) 는 14조 1,564억원으로 전기말 8조 9,209억원 대비 5조 2,354억원 증가하였습니다. 순차입금은 8조 5,274억원이며, 전기말 20조 5,477억원의 순차입금 대비 12조 203억원 감소하였습니다 .\n (*) 현금 및 현금성 자산 합계 = 현금및현금성자산 + 단기금융상품 + 단기투자자산 \n [순현금(순차입금) 변동내역] \n (단위: 백만원) \n 제77기 \n 제76기 \n 제75기 \n 현금및현금성자산 \n 11,205,117 \n 7,587,329 \n 4,977,007 \n 단기금융상품 및 단기투자자산 \n 2,951,246 \n 1,333,589 \n 1,431,985 \n 현금및현금성자산 합계 \n 14,156,363 \n 8,920,918 \n 6,408,992 \n 차입금(유동) \n 5,252,238 \n 9,857,189 \n 7,423,247 \n 차입금(비유동) \n 17,431,495 \n 19,611,443 \n 15,571,357 \n 차입금 합계 \n 22,683,733 \n 29,468,632 \n 22,994,604 \n 순현금(순차입금) \n (8,527,370) \n (20,547,714) \n (16,585,612) \n 개별 기업의 단기적인 유동성의 건전성 수준을 가늠해 볼 수 있는 대표적인 재무비율은 유동비율과 당좌비율이 있으며, 2024년말 기준 당사의 해당 재무비율 현황은 하기와 같습니다. \n [당사 유동성 비율 추이] \n (단위: 백만원) \n 제77기 \n 제76기 \n 제75기 \n 유동비율(= ① / ②) \n 1.7배 \n 1.5배 \n 1.4배 \n ①유동자산 \n 42,278,887 \n 30,468,100 \n 28,733,332 \n ②유동부채 \n 24,965,444 \n 21,007,810 \n 19,843,696 \n 당좌비율(= (① + ②) / ③) \n 1.1배 \n 0.7배 \n 0.6배 \n ①현금 및 현금성 자산 총액(*) \n 14,156,363 \n 8,920,918 \n 6,408,992 \n ②매출채권 \n 13,019,006 \n 6,600,273 \n 5,186,054 \n ③유동부채 \n 24,965,444 \n 21,007,810 \n 19,843,696 \n ※ 현금 및 현금성 자산 총액 = 현금및현금성자산 + 단기금융상품 + 단기투자자산 \n 최근 3년간 당사의 유\n 동비율은 1.4배 ~ 1.7배, 당좌비율은 0.6배 ~ 1.1배 로 적정 수준의 유동성을 유지하고 있으며 회사의 우수한 대외 신인도에 기반한 외부자금 조달능력 등을 감안할 때, 향후 1년 기간내 회사의 유동성 위험이 발생할 가능성은 낮을 것으로 판단하고 있습니다.\n [당사 대외 신용등급 현황] \n 구분 \n 제77기말 \n 제76기말 \n 국내 \n 한국기업평가 \n AA \n AA \n 한국신용평가 \n AA \n AA \n NICE신용평가 \n AA \n AA \n 해외 \n Moody's \n Baa2 \n Baa2 \n S&P \n BBB \n BBB- \n Fitch \n BBB \n BBB \n 당사는 여유있는 유동성이 확보될 수 있도록 적절한 만기나 충분한 유동성을 제공해주는 정기예금, 수시입출금식 예금 등의 금융상품을 선택하여 잉여자금을 투자하고 있습니다. \n 2024년말 기준 회사와 종속기업이 보유하고 있는 전체 현금 및 현금성 자산 중 만기 3개월 이내의 현금 및 현금성 자산은 11조 2,051억원, 만기 1년 이내의 단기금융상품과 단기투자자산은 각각 2조 3,820억원, 5,692억원이며, 사용이 제한되어 있는 금융상품은 중소기업 지원을 위한 은행예금 2,225억원(상생펀드) 등 총 3,406억원입니다. (연결재무제표 주석 '7. 사용제한 금융상품' 참조) \n 차입금 현황 \n (1) 차입금 잔액의 변동 \n 당사는 2024년 중 주요 금융기관 등으로부터 8조 7,180억원을 신규로 조달하였으며, 회사채 및 금융기관차입금의 만기도래로 16조 936억원을 상환하였습니다. 2024년말 당사의 연결 기준 차입금 잔액은 전기말 29조 4,686억원 대비 약 6조 7,849억원 감소하였습니다. \n (단위: 백만원) \n 제77기말 \n 제76기말 \n 증감(*) \n 금융기관차입금 \n 7,448,815 \n 16,278,682 \n (8,829,867) \n 회사채 \n 15,234,918 \n 13,189,950 \n 2,044,968 \n 기타 \n 0 \n 0 \n - \n 계 \n 22,683,733 \n 29,468,632 \n (6,784,899) \n 가중평균차입이자율 \n 3.99% \n 4.50% \n - \n (*) 차입금의 증감에는 외화차입금에 대한 외화환산손익이 포함되어 있습니다. \n (2) 만기도래 현황 \n 당사는 만기 기간별 분류에 기반한 유동성 전략 및 계획을 통하여 유동성 위험을 관리하고 있습니다. 당기말 현재 연결실체가 보유한 금융부채의 계약상 만기는 다음과 같으며, 이러한 금융부채의 조기상환의무는 없습니다. \n (단위: 백만원) \n 1년 이하 \n 1년에서 2년 이하 \n 2년에서 5년 이하 \n 5년 초과 \n 합계 \n 금융기관차입금 \n 2,347,530 \n 2,737,254 \n 2,328,002 \n 454,782 \n 7,867,566 \n 회사채 \n 1,497,275 \n 3,995,330 \n 8,890,576 \n 3,791,700 \n 18,174,883 \n 계 \n 3,844,805 \n 6,732,584 \n 11,218,578 \n 4,246,482 \n 26,042,449 \n 만기비중 \n 15% \n 26% \n 43% \n 16% \n 100% \n ※ 금융부채의 만기에는 차입금에 대한 이자가 포함되어 있습니다. \n (3) 조달자금과 관련된 이행조건 여부당사가 발행한 공모 사채에는 투자자 보호를 위한 재무비율 유지, 담보권 설정제한, 자산처분액 제한 등의 의무조건이 부과되어 있으며, 당사는 이와 같은 의무조건을 준수하고 있습니다. \n 리스 현황 \n 당사의 당기말 현재 리스부채와 관련된 미래 지급할 각 기간별 최소리스료의 총합계와 현재가치, 유동성 구분 내역은 다음과 같습니다. \n (단위: 백만원) \n 구분 \n 리스료지급액 \n 1년 이내 \n 602,620 \n 1년 초과~5년 이내 \n 1,524,900 \n 5년 초과 \n 1,128,611 \n 12월 31일 현재 할인되지 않은 리스부채 \n 3,256,131 \n 12월 31일 현재 연결재무상태표에 인식된 리스부채 \n 2,768,376 \n 유동 리스부채 \n 588,355 \n 비유동 리스부채 \n 2,180,021 \n 자금 지출 관련 당사는 2020년 인텔의 Non-Volatile Memory Solutions Group의 옵테인 사업부를 제외한 NAND 사업부문 전체를 인수하는 영업양수도 계약을 체결하였으며, 2021년 12월, NAND 사업부문 인수 1단계 절차를 완료하였습니다.\n ※ 상기 영업양수도에 관한 상세한 내용은 \n 2021년 12월 30일 정정공시된 '\n 주요사항보고서(영업양수결정) '를 참고하시기 바랍니다.\n 4. 부외거래 \n 연결회사와 관련하여 계류 중인 중요한 소송사건 및 클레임은 중국 반독점법 위반여부에 대한 조사가 있습니다. 당기말 현재 당사는 동 조사의 최종결과를 예측할 수 없습니다.당기말 현재 회사는 상기 소송 외에 지적재산권 등과 관련하여 여러 분쟁에 대응하고있으며, 과거 사건에 의한 현재 의무이고 향후 자원의 유출가능성이 높으며 손실금액을 신뢰성 있게 추정할 수 있는 경우 동 금액을 부채로 인식하고 있습니다. 당사의 부외거래에 관한 자세한 내용은 'Ⅲ. 재무에 관한 사항' - '3. 연결재무제표 주석' 및 '5. 재무제표 주석' 내 '우발부채와 약정사항'을 참고하시기 바랍니다.\n 5. 그 밖에 투자의사결정에 필요한 사항 \n 중요한 회계정책 및 추정에 관한 사항 \n 연결회사는 2024년 1월 1일로 개시하는 회계기간부터 다음의 제ㆍ개정 기준서 및 해석서를 신규로 적용하였습니다. \n (1) 기업회계기준서 제1001호 '재무제표 표시' 개정 - 부채의 유동/비유동 분류, 약정사항이 있는 비유동부채 \n 보고기간말 현재 존재하는 실질적인 권리에 따라 유동 또는 비유동으로 분류되며, 부채의 결제를 연기할 수 있는 권리의 행사가능성이나 경영진의 기대는 고려하지 않습니다. 또한, 부채의 결제에 자기지분상품의 이전도 포함되나, 복합금융상품에서 자기 지분상품으로 결제하는 옵션이 지분상품의 정의를 충족하여 부채와 분리하여 인식된 경우는 제외됩니다. 또한, 기업이 보고기간말 후에 준수해야하는 약정은 보고기간말에 해당 부채의 분류에 영향을 미치지 않으며, 보고기간 이후 12개월 이내 약정사항을 준수해야하는 부채가 보고기간말 현재 비유동부채로 분류된 경우 보고기간 이후 12개월 이내 부채가 상환될 수 있는 위험에 관한 정보를 공시해야 합니다. 해당 기준서의 개정이 재무제표에 미치는 중요한 영향은 없습니다. \n (2) 기업회계기준서 제1007호 '현금흐름표', 기업회계기준서 제1107호 '금융상품: 공시' 개정 - 공급자금융약정에 대한 정보 공시 \n 공급자금융약정을 적용하는 경우, 재무제표이용자가 공급자금융약정이 기업의 부채와 현금흐름 그리고 유동성위험 익스포저에 미치는 영향을 평가할 수 있도록 공급자금융약정에 대한 정보를 공시해야 합니다. 연결회사는 공급자금융약정에 대한 정보를 주석 5에 공시하고 있습니다. \n (3) 기업회계기준서 제1116호 '리스' 개정 - 판매후리스에서 생기는 리스부채 \n 판매후리스에서 생기는 리스부채를 후속적으로 측정할 때 판매자-리스이용자가 보유하는 사용권 관련 손익을 인식하지 않는 방식으로 리스료나 수정리스료를 산정합니다. 해당 기준서의 제정이 재무제표에 미치는 중요한 영향은 없습니다. \n (4) 기업회계기준서 제1001호 '재무제표 표시' 개정 - '가상자산 공시' \n 가상자산을 보유하는 경우, 가상자산을 고객을 대신하여 보유하는 경우, 가상자산을 발행한 경우의 추가 공시사항을 규정하고 있습니다. 해당 기준서의 개정이 재무제표에 미치는 중요한 영향은 없습니다. \n 당사의 중요한 회계정책 및 추정에 관한 사항은 'III. 재무에 관한 사항' - '3. 연결재무제표 주석' - '2. 중요한 회계정책 '을 참고하시기 바랍니다. \n 환경 및 종업원 등에 관한 사항 당사의 환경관련 제재 및 이행현황 등에 관한 사항은 'XI. 그밖에 투자자 보호를 위하여 필요한 사항' - '3. 제재 등과 관련된 사항'을 참고하시기 바랍니다.종업원과 관련하여 주요 핵심인력 이동 등 회사 인력의 중요한 변동은 없었으며, 종업원 현황 등 종업원과 관련된 구체적인 사항은 'Ⅷ. 임원 및 직원 등에 관한 사항'을 참고하시기 바랍니다.\n 법규상의 규제에 관한 사항 당사가 영위하는 사업과 관련된 법규상 주요 규제내용에 관한 사항은 'Ⅱ. 사업의 내용' - '7. 기타 참고사항' - '마. 정부나 지방자치단체의 법률 규정 등에 의한 규제사항'을 참고하시기 바랍니다. \n 파생상품 및 위험관리정책에 관한 사항 당사의 주요 파생상품 및 위험관리정책은 'II. 사업의 내용' - '5. 위험관리 및 파생거래' 및 'Ⅲ. 재무에 관한 사항' - '3. 연결재무제표 주석'을 참고하시기 바랍니다.\n V."
    },
    "2023Q4": {
      "key": "2023Q4",
      "label": "2023 4분기",
      "reportName": "사업보고서 (2023.12)",
      "rcept_no": "20240319000684",
      "text": "이사의 경영진단 및 분석의견 \n 예측정보에 대한 주의사항 본 사업보고서의 '이사의 경영진단 및 분석의견'은 당사의 사업 및 재무현황과 2023년도 영업실적에 대한 투자자의 전반적인 이해를 돕고자 하기와 같은 내용으로 구성하였으며, 본 '이사의 경영진단 및 분석의견' 항목에 포함된 모든 재무제표 및 관련된 분석 의견은 연결 기준으로 작성되었으니 참고하시기를 바랍니다. 1. 개요 2. 재무상태 및 영업실적 3. 유동성 관리정책 및 현황 4. 부외거래 5. 그 밖에 투자의사결정에 필요한 사항\n 본 자료는 미래에 대한 예측정보를 포함하고 있습니다. 예측정보는 과거가 아닌 미래사건과 관계된 회사의 믿음ㆍ기대에 대한 진술이며, 향후 예상되는 회사의 경영현황 및 재무실적과 관련된 정보를 의미합니다. 그러한 예측정보는 위험과 불확실성, 그리고 회사의 실제 실적과 예측진술에 기재되거나 암시된 미래실적 간의 중대한 차이를 초래하는 다른 요인들을 내포하고 있습니다. \n 회사는 본 자료에 포함된 정보의 정확성과 완벽성에 대해서 암묵적으로든 또는 명시적으로든 보장할 수 없으며, 본 자료에 서술된 내용은 과거 또는 미래에 대한 약속이나 진술로 간주될 수 없습니다. 예측정보는 회사의 현재 계획, 추정 및 전망, 그리고 회사가 미래에 처하게 될 정치ㆍ경제적 환경에 근거하고 있으므로, 이용자들은 이러한 예측진술을 적정수준 이상으로 신뢰하여서는 안됩니다. \n 예측정보는 작성일 현재 시점에 기초하여 작성된 것이며, 당사는 동 예측정보 작성시점 이후에 발생하는 위험 또는 불확실성을 반영하기 위하여 예측정보에 기재한 사항을 수정하는 정정보고서를 공시할 의무는 없습니다. \n 1. 개요 \n 2023년 메모리 시장은 각국의 고금리 기조와 경기 침체에 대한 우려 속에 극심한 Downturn을 경험하였습니다. 당사는 이러한 여건에도 불구하고, 기 구축된 프리미엄 제품 포트폴리오를 통한 신속한 대응과 비용 최적화로 수익성을 극대화하고자 노력하였습니다. \n DDR5 및 HBM3 등 고부가가치 제품 판매 확대와 비용 절감 노력에도 불구하고, 메모리 시장 전반의 가격급락으로 인해 연결기준 매출은 32.8조원으로 전년 대비 11.9조원 감소하였으며, 연간 7.7조원의 영업적자를 기록하였습니다. 당기 영업이익률은 -23.6%입니다. \n [주요 경영지표] \n (단위: 백만원) \n 제76기 \n 제75기 \n 제74기 \n 매출액(A) \n 32,765,719 \n 44,621,568 \n 42,997,792 \n 영업이익(B) \n (7,730,313) \n 6,809,417 \n 12,410,340 \n 영업이익률(B/A) \n -23.6% \n 15.3% \n 28.9% \n 메모리 반도체 제조업은 끊임없는 기술 개발과 함께 양산 능력 확대를 통한 원가 경쟁력 강화가 필요한 산업이며, 이를 위해서는 대규모 투자가 필수적입니다.\n 최근 3년간 투자 추이를 살펴보면, 2021년은 비대면 수요 확산에 따른 우호적인 메모리 시장 환경이 조성됨과 함께 직전연도 대비 약 3.3조원 증가한 13.4조원을 집행하였습니다. 2022년은 장비와 인프라 확보 \n 등을 위한 투자가 증가하며 Solidigm을 포함하여 유형자산 취득액 기준 19.6조원의 투자를 집행하였습니다 \n . \n 2023년은 수익성 확보를 위해 보수적 투자를 시행하여 \n Solidigm을 포함한 \n 유형자산 취득액 기준 \n 6.6조원의 투자를 집행하였습니다. \n 2024년 메모리 시장은 AI를 중심으로, On-Device AI 등 새로운 패러다임의 본격화가 전망됩니다. PC, Mobile, 일반 Server 등 전통적인 메모리 수요처 역시 회복 가능성을 보이며, 전반적인 업황 회복이 기대됩니다. 당사는 이러한 패러다임 변화에 발 맞춰 AI Infra향 메모리의 기술 및 제품 경쟁력 강화에 힘쓰겠습니다. 또한, 이를 기반으로 고객 수요에 적극적으로 대응하여 신규 시장을 주도하는 데에 최선의 노력을 기울이겠습니다. \n 2. 재무상태 및 영업실적 \n [요약 손익계산서] \n (단위: 백만원) \n 과 목 \n 제76기 \n 제75기 \n 증감 \n I. 매출액 \n 32,765,719 \n 44,621,568 \n (11,855,849) \n II. 매출원가 \n 33,299,167 \n 28,993,713 \n 4,305,454 \n III. 매출총이익(손실) \n (533,448) \n 15,627,855 \n (16,161,303) \n IV. 판매비와관리비 \n 7,196,865 \n 8,818,438 \n (1,621,573) \n V. 영업이익(손실) \n (7,730,313) \n 6,809,417 \n (14,539,730) \n VI. 순영업외비용(이익) \n 3,927,503 \n 2,806,637 \n 1,120,866 \n VII. 법인세비용차감전순이익(손실) \n (11,657,816) \n 4,002,780 \n (15,660,596) \n VIII. 법인세비용(수익) \n (2,520,269) \n 1,761,111 \n (4,281,380) \n IX. 당기순이익(손실) \n (9,137,547) \n 2,241,669 \n (11,379,216) \n ※ 상기 표의 재무정보는 주주총회 승인전 재무제표이며 향후 정기주주총회에서 재무제표 승인 관련 안건이 부결되거나 수정이 발생한 경우 정정보고서를 통해 그 내용 및 사유 등을 반영할 예정입니다. \n 매출 \n 제76기 당사 매출액은 32조 7,657억원으로 반도체 시황 악화에 따른 주요 제품 판가 하락 영향으로 전년 44조 6,216억원 대비 27% 감소하였습니다. 제품군별로는 전체 매출 중 DRAM과 NAND가 각각 63%와 29% 비중을 차지하였으며, 그 외 기타 매출은 7%를 차지하였습니다. \n 영업이익 \n 당기 영업손실은 7조 7,303억원으로 반도체 시황 악화에 따른 판가 하락 및 재고평가손실 영향으로 전기 대비 14조 5,397억원 감소, 적자전환하였습니다. 당기 순영업외비용은 장기투자자산평가손실 및 파생상품손실 증가로 전년 대비 1조 1,209억원 증가하였으며, 법인세차감전순손실은 전기대비 15조 6,606억 감소한 11조 6,578억원을 기록(적자전환)하였으며, 당기순손실은 전년 대비 11조 3,792억원 감소한 9조 1,375억원을 기록(적자전환)하였습니다. \n R&D 비용 \n 당사의 신규 제품 개발 프로젝트는 1)검토 및 기획단계와 2)제품 설계 및 양산화 단계로 구분될 수 있습니다. 당사는 새로운 제품 개발 시 '검토 및 기획 단계' 에서 발생한 지출은 경상개발비로 인식하여 당기 비용으로 반영하고 있으며, 이후 '제품 설계 및 양산화 단계' 에서 발생한 지출은 무형자산(개발비)으로 인식하여 일정한 기간 동안 상각하는 방식으로 비용을 인식하고 있습니다.\n 제품 개발 활동 관련하여 발생한 비용 중 '검토 및 기획 단계'에서 발생한 개발활동 관련 비용은 총 3조 7,501억원으로 당기 경상개발비로 비용을 인식하였습니다. 그 외 '제품 설계 및 양산화 단계' 기준을 충족하는 총 3,510억원은 개발비로 자산화하였습니다. \n [요약 재무상태표] \n (단위: 백만원) \n 구 분 \n 제76기 \n 제75기 \n 제74기 \n I. 유동자산 \n 30,468,100 \n 28,733,332 \n 26,907,075 \n ㆍ현금및현금성자산 \n 7,587,329 \n 4,977,007 \n 5,057,982 \n ㆍ단기금융상품 \n 472,617 \n 415,625 \n 474,637 \n ㆍ단기투자자산 \n 860,972 \n 1,016,360 \n 3,139,923 \n ㆍ매출채권 \n 6,600,273 \n 5,186,054 \n 8,267,111 \n ㆍ기타수취채권 \n 357,641 \n 272,512 \n 171,464 \n ㆍ재고자산 \n 13,480,659 \n 15,664,707 \n 8,950,087 \n ㆍ기타유동자산 \n 1,079,168 \n 1,201,067 \n 845,871 \n II. 비유동자산 \n 69,862,065 \n 75,138,180 \n 69,439,450 \n ㆍ관계기업 및 공동기업투자 \n 1,367,348 \n 1,352,845 \n 1,410,428 \n ㆍ장기투자자산 \n 4,105,704 \n 5,733,544 \n 6,665,513 \n ㆍ유형자산 \n 52,704,853 \n 60,228,528 \n 53,225,667 \n ㆍ무형자산 \n 3,834,567 \n 3,512,107 \n 4,797,162 \n ㆍ기타비유동자산 \n 7,849,593 \n 4,311,156 \n 3,340,680 \n 자 산 총 계 \n 100,330,165 \n 103,871,512 \n 96,346,525 \n I. 유동부채 \n 21,007,810 \n 19,843,696 \n 14,735,395 \n II. 비유동부채 \n 25,818,603 \n 20,737,274 \n 19,420,072 \n 부 채 총 계 \n 46,826,413 \n 40,580,970 \n 34,155,467 \n I. 자본금 \n 3,657,652 \n 3,657,652 \n 3,657,652 \n II. 자본잉여금 \n 4,372,559 \n 4,336,170 \n 4,334,643 \n III. 기타자본 \n (2,269,294) \n (2,311,409) \n (2,294,562) \n IV. 기타포괄손익누계액 \n 1,014,055 \n 898,682 \n 675,271 \n V. 이익잉여금 \n 46,729,313 \n 56,685,260 \n 55,784,068 \n VI. 비지배지분 \n (533) \n 24,187 \n 33,986 \n 자 본 총 계 \n 53,503,752 \n 63,290,542 \n 62,191,058 \n 부 채 와 자 본 총 계 \n 100,330,165 \n 103,871,512 \n 96,346,525 \n ※ 상기 표의 재무정보는 주주총회 승인전 재무제표이며 향후 정기주주총회에서 재무제표 승인 관련 안건이 부결되거나 수정이 발생한 경우 정정보고서를 통해 그 내용 및 사유 등을 반영할 예정입니다. \n 자산 \n 당기말 자산 총액은 전기 대비 3조 5,413억원(3.4%) 감소한 100조 3,302억원입니다.자산의 주요 감소 원인은 재고자산 2조 1,840억원 감소 및 투자 집행 축소에 따른 유형자산 7조 5,237억원 감소 영향입니다. \n 부채 \n 당기말 부채 총액은 전기대비 6조 2,454억(15.4%) 증가한 46조 8,264억원입니다. 유동부채가 1조 1,641억(5.9%) 증가하였고, 비유동부채가 5조 813억(24.5%) 증가하였습니다. 부채의 주요 변동 원인으로는 차입금 실행 증가로 인한 총차입금이 6조 4,740억원 증가하였습니다. \n 자본 \n 당기말 자본 총액은 전기 대비 9조 7,868억(15.5%) 감소한 53조 5,038억원으로, 주요 감소 원인은 시황 악화에 따른 당기순손실 9조 1,375억원 발생 및 배당금지급 8,256억원 등입니다. \n 신규 및 중단 사업 해당사항 없습니다.\n 경영합리화 관련 해당사항 없습니다.\n 환율 변동 영향 외환위험은 미래예상거래, 인식된 자산과 부채 및 해외사업장에 대한 순투자가 기능통화 외의 통화로 표시될 때 발생합니다.당사는 영업 측면에서 매출의 대부분이 환율 변동 위험에 노출되어 있고, 생산을 위한 원부자재와 투자 관련 지출의 상당 비중이 환율 변동에 영향을 받고 있습니다.이에 당사는 외화표시 자산 및 부채에 대해 환율변동에 의한 리스크를 최소화하여 재무구조의 건전성 및 경영 안정성 제고를 목표로 환 리스크 관리에 만전을 기하고 있습니다.\n 당기말 현재 연결회사의 화폐성 외화자산 및 외화부채의 내역은 다음과 같습니다. \n (원화단위: 백만원, 외화단위: 외화 백만단위) \n 구 분 \n 자 산 \n 부 채 \n 현지통화 \n 원화환산 \n 현지통화 \n 원화환산 \n USD \n 17,710 \n 22,834,834 \n 21,904 \n 28,243,132 \n JPY \n 544 \n 4,961 \n 72,602 \n 662,607 \n CNY \n 1,631 \n 294,926 \n 3,490 \n 631,184 \n EUR \n 17 \n 24,680 \n 139 \n 197,932 \n 또한, 연결회사는 외화사채 및 차입금의 환위험을 회피하기 위하여 주석 22에서 설명하는 바와 같이 통화스왑계약 및 통화이자율스왑계약을 체결하고 있습니다. \n 당기말 현재 각 외화에 대한 기능통화의 환율이 10% 변동시, 동 환율변동이 법인세비용차감전순이익에 미치는 영향은 다음과 같습니다. \n (단위: 백만원) \n 구 분 \n 10% 상승시 \n 10% 하락시 \n USD \n (332,123) \n 332,123 \n JPY \n (65,765) \n 65,765 \n CNY \n (33,626) \n 33,626 \n EUR \n (17,325) \n 17,325 \n 자산손상 또는 감액손실 \n 당사는 종업원급여에서 발생한 자산, 재고자산, 이연법인세자산을 제외한 모든 비금융자산에 대해서는 매 보고기간말마다 자산손상을 시사하는 징후가 있는지를 검토하며, 만약 그러한 징후가 있다면 당해 자산의 회수가능액을 추정하고 있습니다. 단, 사업결합으로 취득한 영업권 및 내용연수가 비한정인 무형자산, 아직 사용할 수 없는 무형자산에 대해서는 자산손상을 시사하는 징후와 관계없이 매년 회수가능액과 장부금액을 비교하여 손상검사를 하고 있습니다. \n 회수가능액은 개별 자산별로, 또는 개별 자산의 회수가능액을 추정할 수 없다면 그 자산이 속하는 현금창출단위별로 회수가능액을 추정하고 있으며, 회수가능액은 사용가치와 순공정가치 중 큰 금액으로 결정하고 있습니다. \n 연결회사는 당기 중 미래 경제적 효익의 창출에 기여하지 못할 것으로 예상되는 일부 기계장치에 대하여 손상차손 1,657억원을 인식하였으 \n 며, 당기 중 회수가능가액이 장부가액에 미달하는 개발프로젝트들에 대해 총 1,670억원의 \n 손상차손을 인식하였습니다. \n 계정과목별로는 유형자산손상차손 1,657억원, 무형자산손상차손 1,670억원 등을 인식하였습니다. \n 당사의 자산손상에 대한 구체적인 내용은 'Ⅲ. 재무에 관한 사항' - '3. 연결재무제표 주석'을 참고하시기를 바랍니다.\n 3. 유동성 관리정책 및 현황 \n 당기말 현재 회사가 보유 중인 현금 및 현금성 자산 합계(*) 는 8조 9,209억원으로 전기말 6조 4,090억원 대비 2조 5,119억원 증가하였습니다. 순차입금은 20조 5,477억원이며, 전기말 16조 5,856억원 대비 3조 9,621억원 증가하였습니다. (*) 현금 및 현금성 자산 합계 = 현금및현금성자산 + 단기금융상품 + 단기투자자산\n [순현금(순차입금) 변동내역] \n (단위: 백만원) \n 제76기 \n 제75기 \n 제74기 \n 현금및현금성자산 \n 7,587,329 \n 4,977,007 \n 5,057,982 \n 단기금융상품 및 단기투자자산 \n 1,333,589 \n 1,431,985 \n 3,614,560 \n 현금및현금성자산 합계 \n 8,920,918 \n 6,408,992 \n 8,672,542 \n 차입금(유동) \n 9,857,189 \n 7,423,247 \n 2,880,763 \n 차입금(비유동) \n 19,611,443 \n 15,571,357 \n 14,743,046 \n 차입금 합계 \n 29,468,632 \n 22,994,604 \n 17,623,809 \n 순현금(순차입금) \n (20,547,714) \n (16,585,612) \n (8,951,267) \n 개별 기업의 단기적인 유동성의 건전성 수준을 가늠해 볼 수 있는 대표적인 재무비율은 유동비율과 당좌비율이 있으며, 2023년말 기준 당사의 해당 재무비율 현황은 하기와 같습니다. \n [당사 유동성 비율 추이] \n (단위: 백만원) \n 제76기 \n 제75기 \n 제74기 \n 유동비율(= ① / ②) \n 1.5배 \n 1.4배 \n 1.8배 \n ①유동자산 \n 30,468,100 \n 28,733,332 \n 26,907,075 \n ②유동부채 \n 21,007,810 \n 19,843,696 \n 14,735,395 \n 당좌비율(= (① + ②) / ③) \n 0.7배 \n 0.6배 \n 1.1배 \n ①현금 및 현금성 자산 총액(*) \n 8,920,918 \n 6,408,992 \n 8,672,542 \n ②매출채권 \n 6,600,273 \n 5,186,054 \n 8,267,111 \n ③유동부채 \n 21,007,810 \n 19,843,696 \n 14,769,356 \n ※ 현금 및 현금성 자산 총액 = 현금및현금성자산 + 단기금융상품 + 단기투자자산 최근 3년간 당사의 유동비율은 1.4 ~ 1.8배, 당좌비율은 0.6 ~ 1.1배로 적정 수준의 유동성을 유지하고 있으며, 회사의 우수한 대외 신인도에 기반한 외부자금 조달능력 등을 감안할 때, 향후 1년 기간내 회사의 유동성 위험이 발생할 가능성은 낮을 것으로 판단하고 있습니다.\n [당사 대외 신용등급 현황] \n 구분 \n 제76기말 \n 제75기말 \n 국내 \n NICE신용평가 : AA \n NICE신용평가 : AA \n 한국기업평가 : AA \n 한국기업평가 : AA \n 한국신용평가 : AA \n 한국신용평가 : AA \n 해외 \n Moody's : Baa2 \n Moody's : Baa2 \n S&P : BBB- \n S&P : BBB- \n Fitch : BBB \n - \n 당사는 여유있는 유동성이 확보될 수 있도록 적절한 만기나 충분한 유동성을 제공해주는 정기예금, 수시입출금식 예금 등의 금융상품을 선택하여 잉여자금을 투자하고 있습니다. \n 2023년말 기준 회사와 종속기업이 보유하고 있는 전체 현금 및 현금성 자산 중 만기 3개월 이내의 현금 및 현금성 자산은 7조 5,873억원, 만기 1년 이내의 단기금융상품과 단기투자자산은 각각 4,726억원, 8,610억원이며, 사용이 제한되어 있는 금융상품은 중소기업 지원을 위한 은행예금 2,225억원(상생펀드) 등 총 2,303억원입니다. (연결 재무제표 주석 '7. 사용제한 금융상품' 참조) \n 차입금 현황 \n (1) 차입금 잔액의 변동 \n (단위: 백만원) \n 제76기말 \n 제75기말 \n 증감* \n 금융기관차입금 \n 16,278,682 \n 15,527,010 \n 751,672 \n 회 사 채 \n 13,189,950 \n 7,467,594 \n 5,722,356 \n 기 타 \n 0 \n 0 \n - \n 계 \n 29,468,632 \n 22,994,604 \n 6,474,028 \n 가중평균차입이자율 \n 4.50% \n 3.97% \n - \n (*) 차입금의 증감에는 외화차입금에 대한 외화환산손익이 포함되어 있습니다. \n 당사는 2023년 중 주요 금융기관 등으로부터 20조 6,580억원을 신규로 조달하였으며, 회사채 및 금융기관차입금의 만기도래로 13조 6,894억원을 상환하였습니다.2023년말 당사의 연결 기준 차입금 잔액은 29조 4,686억원으로 전기말 22조 9,946억원 대비 약 6조 4,740억원 증가하였습니다. \n (2) 만기도래 현황 \n 당사는 만기 기간별 분류에 기반한 유동성 전략 및 계획을 통하여 유동성 위험을 관리하고 있습니다. 당기말 현재 연결실체가 보유한 금융부채의 계약상 만기는 다음과 같으며, 이러한 금융부채의 조기상환의무는 없습니다. \n (단위: 백만원) \n 1년 이하 \n 1년에서 2년 이하 \n 2년에서 5년 이하 \n 5년 초과 \n 합계 \n 금융기관차입금 \n 6,545,365 \n 4,941,746 \n 5,717,888 \n 558,472 \n 17,763,471 \n 회 사 채 \n 2,490,518 \n 1,253,321 \n 8,399,143 \n 3,701,912 \n 15,844,894 \n 계 \n 9,035,883 \n 6,195,067 \n 14,117,031 \n 4,260,384 \n 33,608,365 \n 만 기 비 중 \n 27% \n 18% \n 42% \n 13% \n 100% \n ※ 금융부채의 만기에는 차입금에 대한 이자가 포함되어 있습니다. \n (3) 조달자금과 관련된 이행조건 여부당사가 발행한 공모사채에는 투자자 보호를 위한 재무비율 유지, 담보권 설정제한, 자산처분액 제한 등의 의무조건이 부과되어 있으며, 당사는 이와 같은 의무조건을 준수하고 있습니다. \n 리스 현황 \n 당사의 당기말 현재 리스부채와 관련된 미래 지급할 각 기간별 최소리스료의 총합계와 현재가치, 유동성 구분 내역은 다음과 같습니다. \n (단위: 백만원) \n 구 분 \n 리스료지급액 \n 1년 이내 \n 643,261 \n 1년 초과~5년 이내 \n 1,584,386 \n 5년 초과 \n 1,273,853 \n 12월 31일 현재 할인되지 않은 리스부채 \n 3,501,500 \n 12월 31일 현재 연결재무상태표에 인식된 리스부채 \n 3,029,874 \n 유동 리스부채 \n 631,497 \n 비유동 리스부채 \n 2,398,377 \n 자금 지출 관련 당사는 2020년 인텔의 Non-Volatile Memory Solutions Group의 옵테인 사업부를 제외한 NAND 사업 부문 전체를 인수하는 영업양수도 계약을 체결하였으며, 2021년 12월, NAND 사업부문 인수 1단계 절차를 완료하였습니다.인수 2단계 예상 시점인 2025년 3월에 지급할 금액은 USD 20억 수준으로 예상되며,해당 자금은 보유 현금 및 차입 등을 통해 조달할 예정입니다.※ 상기 영업양수도에 관한 상세한 내용은 2020년 10월 22일 정정공시된 '\n 주요사항보고서(영업양수결정) '를 참고하시기를 바랍니다.\n 4. 부외거래 \n 연결회사와 관련하여 계류 중인 중요한 소송사건 및 클레임은 중국 반독점법 위반조사 및 SK hynix America Inc.를 상대로 한 북미지역 내 가격 담합 집단소송 등이 있습니다. 당기말 현재 미국 직접 구매자 및 간접 구매자 집단 소송은 모두 1심 기각 결정을 유지하는 것으로 최종 종료되었습니다.또한, 지난 2020년에 체결한 인텔의 Non-Volatile Memory Solutions Group의 옵테인 사업을 제외한 NAND 사업 전체(이하 \"인텔NAND사업\")를 인수하는 영업양수도 계약 관련하여 2차 종결이 예상되는 2025년 3월까지 잔금 USD 2,235백만을 지급할 예정입니다. 당사는 향후 자원의 유출가능성이 높으며 손실금액을 신뢰성 있게 추정할 수 있는 경우 동 금액을 부채로 인식하고 있습니다.당사의 부외거래에 관한 자세한 내용은 'Ⅲ. 재무에 관한 사항' - '3. 연결재무제표 주석' 및 '5. 재무제표 주석' 내 '우발부채와 약정사항'을 참고하시기를 바랍니다.\n 5. \n 그 밖에 투자의사결정에 필요한 사항 \n 중요한 회계정책 및 추정에 관한 사항 \n 연결회사는 2023년 1월 1일로 개시하는 회계기간부터 다음의 제ㆍ개정 기준서 및 해석서를 신규로 적용하였습니다. \n (1) 기업회계기준서 제1001호 '재무제표 표시' - '회계정책'의 공시 \n 중요한 회계정책 정보(중요한 회계 정책 정보란, 재무제표에 포함된 다른 정보와 함께 고려되었을 때 재무제표의 주요 이용자의 의사결정에 영향을 미칠 정도의 수준을 의미)를 정의하고 이를 공시하도록 하였습니다. 해당 기준서의 개정이 재무제표에 미치는 중요한 영향은 없습니다. \n (2) 기업회계기준서 제1001호 '재무제표 표시' - 행사가격 조정 조건이 있는 금융부채 평가손익 공시 \n 발행자의 주가 변동에 따라 행사가격이 조정되는 조건이 있는 금융상품의 전부나 일부가 금융부채로 분류되는 경우 그 금융부채의 장부금액과 관련 손익을 공시하도록 하였습니다. 해당 기준서의 개정이 재무제표에 미치는 중요한 영향은 없습니다. \n (3) 기업회계기준서 제1008호 '회계정책, 회계추정의 변경 및 오류' - '회계추정'의 정의 \n 회계추정을 정의하고, 회계정책의 변경과 구별하는 방법을 명확히 하였습니다. 해당 기준서의 개정이 재무제표에 미치는 중요한 영향은 없습니다. \n (4) 기업회계기준서 제1012호 '법인세' - 단일거래에서 생기는 자산과 부채에 대한 이연법인세 \n 자산 또는 부채가 최초로 인식되는 거래의 최초 인식 예외 요건에 거래시점 동일한 가산할 일시적차이와 차감할 일시적차이를 발생시키지 않는 거래라는 요건을 추가하였습니다. 해당 기준서의 개정이 재무제표에 미치는 중요한 영향은 없습니다. \n (5) 기업회계기준서 제1012호 '법인세' - '국제조세개혁 - 필라2 모범규칙' \n 개정 기준은 다국적기업의 국제조세를 개혁하는 필라2 모범규칙을 반영하는 법률의 시행으로 생기는 이연법인세 회계처리를 일시적으로 완화하고 이와 관련된 당기법인세 효과 등에 대한 공시를 요구하고 있습니다. 연결회사는 필라2 규칙과 관련되는 이연법인세의 인식 및 공시에 대한 예외 규정을 적용하였으며, 해당 법률이 2024년 1월 1일부터 시행될 예정이므로 연결회사의 필라2 관련 당기법인세비용은 없습니다. 필라2 법인세의 영향은 주석 30에서 설명하고 있습니다. \n 당사의 중요한 회계정책 및 추정에 관한 사항은 'III. 재무에 관한 사항' - '3. 연결재무제표 주석' - '2. 중요한 회계정책 '을 참고하시기를 바랍니다. \n 환경 및 종업원 등에 관한 사항 당사의 환경관련 제재 및 이행현황 등에 관한 사항은 'XI. 그밖에 투자자 보호를 위하여 필요한 사항' - '3. 제재 등과 관련된 사항'을 참고하시기를 바랍니다.종업원과 관련하여 주요 핵심인력 이동 등 회사 인력의 중요한 변동은 없었으며, 종업원 현황 등 종업원과 관련된 구체적인 사항은 'Ⅷ. 임원 및 직원 등에 관한 사항'을 참조하시기를 바랍니다.\n 법규상의 규제에 관한 사항 당사가 영위하는 사업과 관련된 법규상 주요 규제내용에 관한 사항은 'Ⅱ. 사업의 내용' - '7. 기타 참고사항' - '마. 정부나 지방자치단체의 법률 규정 등에 의한 규제사항'을 참고하시기를 바랍니다. \n 파생상품 및 위험관리정책에 관한 사항 당사의 주요 파생상품 및 위험관리정책은 'II. 사업의 내용' - '5. 위험관리 및 파생거래' 및 'Ⅲ. 재무에 관한 사항' - '3. 연결재무제표 주석'을 참고하시기를 바랍니다.\n V."
    },
    "2022Q4": {
      "key": "2022Q4",
      "label": "2022 4분기",
      "reportName": "사업보고서 (2022.12)",
      "rcept_no": "20230321001209",
      "text": "이사의 경영진단 및 분석의견 \n 예측정보에 대한 주의사항 본 사업보고서의 '이사의 경영진단 및 분석의견'은 당사의 사업 및 재무현황과 2022년도 영업실적에 대한 투자자의 전반적인 이해를 돕고자 하기와 같은 내용으로 구성하였으며, 본 '이사의 경영진단 및 분석의견' 항목에 포함된 모든 재무제표 및 관련된 분석 의견은 연결 기준으로 작성되었으니 참고하시기 바랍니다. 1. 개요 2. 재무상태 및 영업실적 3. 유동성 관리정책 및 현황 4. 부외거래 5. 그 밖에 투자의사결정에 필요한 사항\n 본 자료는 미래에 대한 예측정보를 포함하고 있습니다. 예측정보는 과거가 아닌 미래사건과 관계된 회사의 믿음ㆍ기대에 대한 진술이며, 향후 예상되는 회사의 경영현황 및 재무실적과 관련된 정보를 의미합니다. 그러한 예측정보는 위험과 불확실성, 그리고 회사의 실제 실적과 예측진술에 기재되거나 암시된 미래실적 간의 중대한 차이를 초래하는 다른 요인들을 내포하고 있습니다. \n 회사는 본 자료에 포함된 정보의 정확성과 완벽성에 대해서 암묵적으로든 또는 명시적으로든 보장할 수 없으며, 본 자료에 서술된 내용은 과거 또는 미래에 대한 약속이나 진술로 간주될 수 없습니다. 예측정보는 회사의 현재 계획, 추정 및 전망, 그리고 회사가 미래에 처하게 될 정치ㆍ경제적 환경에 근거하고 있으므로, 이용자들은 이러한 예측진술을 적정수준 이상으로 신뢰하여서는 안됩니다. \n 예측정보는 작성일 현재 시점에 기초하여 작성된 것이며, 당사는 동 예측정보 작성시점 이후에 발생하는 위험 또는 불확실성을 반영하기 위하여 예측정보에 기재한 사항을 수정하는 정정보고서를 공시할 의무는 없습니다. \n 1. 개요 2022년은 COVID-19 재확산, 미-중 무역갈등, 러시아-우크라이나 전쟁에 따른 글로벌 공급망 불안이 지속되고, 인플레이션 대응을 위한 금리 인상 등 사업환경의 불확실성이 심화되었습니다.\n 이러한 불확실성에도 불구하고 SK하이닉스는 업계 선두의 기술력과 품질 경쟁력을 바탕으로, 전년도 실적을 상회하는 연결 기준 매출 44.6조원을 달성하였습니다. 매출 비중은 DRAM이 63%, NAND가 32%였고, Solidigm 편입과 성장하는 Enterprise SSD 제품의 판매가 확대된 영향으로 NAND의 판매 비중이 역대 최고 수준을 경신하였습니다. 반면, 영업이익은 하반기 수요 둔화로 전년 대비 45% 감소한 6.8조원을 기록하였습니다. \n 하반기 수요 둔화로 영업실적이 감소함에 따라 연말 기준 보유현금은 전기 대비 약 2조 2,635억원 감소한 6조 4,090억원을 기록했으며, 차입금은 업황 변동 리스크에 대응하기 위한 사채 발행 등 자금조달 영향으로 전기 대비 5조 3,708억원 증가한 22조 9,946억원을 기록했습니다. \n [당사 보유현금 및 차입금 변동내역] \n (단위: 백만원) \n 제75기 \n 제74기 \n 제73기 \n 현금및현금성자산(*) \n 6,408,992 \n 8,672,542 \n 4,948,215 \n 차입금 합계 \n 22,994,604 \n 17,623,809 \n 11,251,648 \n 순현금(순부채) \n (16,585,612) \n (8,951,267) \n (6,303,433) \n (*) 현금및현금성자산, 단기금융상품 및 단기투자자산의 합계액입니다. \n 메모리 반도체 제조업은 끊임없는 기술 개발과 함께 양산 능력 확대를 통한 원가 경쟁력 강화가 필요한 산업이며, 이를 위해서는 대규모 투자가 필수적입니다. \n 최근 3년간 투자 추이를 살펴보면, 2020년은 COVID-19 발생과 미-중 무역 분쟁이 격화된 영향으로 유형자산 취득액 기준으로 10조원 수준의 투자를 집행하며 보수적인 기조를 유지하였습니다. 2021년은 비대면 수요 확산에 따른 우호적인 메모리 시장 환경이 조성됨과 함께 직전연도 대비 약 3.3조원 증가한 13.4조원을 집행하였습니다. 2022년은 장비와 인프라 확보 등을 위한 투자가 증가하며 Solidigm을 포함하여 19.6조원의 투자를 집행하였습니다 .\n 2023년은 아직 해소되지 않은 거시경제 불확실성과 이에 따른 IT 수요 둔화가 지속될 가능성이 있으며, 당사는 생산과 투자를 효율화하고 업황 변동성을 견딜 수 있는 충분한 유동성을 확보하여 단기적인 업황 부진에 대응할 계획입니다. \n 메모리 수요는 5G 본격화와 비대면 환경으로의 시대적 변화, 자율주행자동차 시대 도래, AI 보편화 등으로 인해 장기적으로 성장할 것으로 전망되고 있습니다. 당사는 단기적인 생산 및 투자 효율화와 함께, HBM 등 차세대 메모리 솔루션 제품과 선행기술 확보, 미래 성장을 위한 인프라 부문에 대한 미래 투자는 지속하여 메모리 수요의 성장성과 고도화를 준비할 계획입니다. \n 2. 재무상태 및 영업실적 \n [요약 손익계산서] \n (단위: 백만원) \n 과 목 \n 제75기 \n 제74기 \n 증감 \n I. 매출액 \n 44,621,568 \n 42,997,792 \n 1,623,776 \n II. 매출원가 \n 28,993,713 \n 24,045,600 \n 4,948,113 \n III. 매출총이익 \n 15,627,855 \n 18,952,192 \n (3,324,337) \n IV. 판매비와관리비 \n 8,818,438 \n 6,541,852 \n 2,276,586 \n V. 영업이익 \n 6,809,417 \n 12,410,340 \n (5,600,923) \n VI. 순영업외비용(이익) \n 2,806,637 \n (1,005,647) \n 3,812,284 \n VII. 법인세차감전순이익 \n 4,002,780 \n 13,415,987 \n (9,413,207) \n VIII. 법인세비용 \n 1,761,111 \n 3,799,799 \n (2,038,688) \n IX. 당기순이익 \n 2,241,669 \n 9,616,188 \n (7,374,519) \n ※ 상기 표의 재무정보는 주주총회 승인전 재무제표이며 향후 정기주주총회에서 재무제표 승인 관련 안건이 부결되거나 수정이 발생한 경우 정정보고서를 통해 그 내용 및 사유 등을 반영할 예정입니다. \n 매출 당기 매출은 44조 6,216억원으로 Solidigm 연결 편입 및 고용량 제품 판매 확대 등으로 전기 42조 9,978억원 대비 4% 증가하였습니다. 제품군별로는 전체 매출 중 DRAM과 NAND가 각각 63%와 32% 비중을 차지하였으며, 그 외 기타 매출은 5%를 차지하였습니다.\n 영업이익 \n 당기 영업이익은 6조 8,094억원으로 메모리 수요 부진으로 인한 판가 하락 및 연말 재고평가손실 확대 영향으로 전기 대비 45% 감소하였습니다. 업황 변동에 따른 가격 하락은 메모리 제품의 수급 상황에 따라 발생하는 통상적인 요인이며, 향후 단기적인 방향성을 예단하기는 어렵습니다.당기 매출원가는 전기 대비 21% 증가하였으며, 판매관리비는 35% 증가하였습니다. 당기 판매비와관리비는 경상개발비 4조 4,746억원, 인건비 1조1,237억원, 지급수수료 1조 951억원 등으로 구성되며, 총 판매비와관리비 중 차지하는 비중은 경상개발비 51%, 인건비 13%, 지급수수료 12% 입니다. \n R&D 비용 \n 당사의 신규 제품 개발 프로젝트는 1)검토 및 기획단계와 2)제품 설계 및 양산화 단계로 구분될 수 있습니다. 당사는 새로운 제품 개발 시 '검토 및 기획 단계' 에서 발생한 지출은 경상개발비로 인식하여 당기 비용으로 반영하고 있으며, 이후 '제품 설계 및 양산화 단계' 에서 발생한 지출은 무형자산으로 인식하여 일정한 기간 동안 상각하는 방식으로 비용을 인식하고 있습니다.제품 개발 활동 관련하여 발생한 비용 중 '검토 및 기획 단계'에서 발생한 개발활동 관련 비용은 총 4조 4,746억원으로 당기 경상개발비로 비용을 인식하였습니다. 그 외 '제품 설계 및 양산화 단계' 기준을 충족하는 총 3,290억원은 무형자산(개발비)으로 인식 하였습니다. \n 기타손익 \n 당기 순영업외수익은 장기투자자산평가손실, 무형자산손상차손, 환차/환산손실, 순이자비용 등을 반영하여 2조 8,066억원을 기록하였습니다.\n [요약 대차대조표] \n (단위: 백만원) \n 구 분 \n 제75기 \n 제74기 \n 제73기 \n I. 유동자산 \n 28,733,332 \n 26,907,075 \n 16,570,953 \n ㆍ현금및현금성자산 \n 4,977,007 \n 5,057,982 \n 2,975,989 \n ㆍ단기금융상품 \n 415,625 \n 474,637 \n 436,708 \n ㆍ단기투자자산 \n 1,016,360 \n 3,139,923 \n 1,535,518 \n ㆍ매출채권 \n 5,186,054 \n 8,267,111 \n 4,931,322 \n ㆍ기타수취채권 \n 272,512 \n 171,464 \n 69,194 \n ㆍ재고자산 \n 15,664,707 \n 8,950,087 \n 6,136,318 \n ㆍ기타유동자산 \n 1,201,067 \n 845,871 \n 485,904 \n II. 비유동자산 \n 75,138,180 \n 69,439,450 \n 54,602,900 \n ㆍ관계기업 및 공동기업투자 \n 1,352,845 \n 1,410,428 \n 1,166,244 \n ㆍ장기투자자산 \n 5,733,544 \n 6,665,513 \n 6,139,627 \n ㆍ유형자산 \n 60,228,528 \n 53,225,667 \n 41,230,562 \n ㆍ무형자산 \n 3,512,107 \n 4,797,162 \n 3,400,278 \n ㆍ기타비유동자산 \n 4,311,156 \n 3,340,680 \n 2,666,189 \n 자 산 총 계 \n 103,871,512 \n 96,346,525 \n 71,173,853 \n I. 유동부채 \n 19,843,696 \n 14,735,395 \n 9,072,360 \n II. 비유동부채 \n 20,737,274 \n 19,420,072 \n 10,192,396 \n 부 채 총 계 \n 40,580,970 \n 34,155,467 \n 19,264,756 \n I. 자본금 \n 3,657,652 \n 3,657,652 \n 3,657,652 \n II. 자본잉여금 \n 4,336,170 \n 4,334,643 \n 4,143,736 \n III. 기타자본 \n (2,311,409) \n (2,294,562) \n (2,503,122) \n IV. 기타포괄손익누계액 \n 898,682 \n 675,271 \n (405,453) \n V. 이익잉여금 \n 56,685,260 \n 55,784,068 \n 46,995,728 \n VI. 비지배지분 \n 24,187 \n 33,986 \n 20,556 \n 자 본 총 계 \n 63,290,542 \n 62,191,058 \n 51,909,097 \n 부 채 와 자 본 총 계 \n 103,871,512 \n 96,346,525 \n 71,173,853 \n ※ 상기 표의 재무정보는 주주총회 승인전 재무제표이며 향후 정기주주총회에서 재무제표 승인 관련 안건이 부결되거나 수정이 발생한 경우 정정보고서를 통해 그 내용 및 사유 등을 반영할 예정입니다. \n 자산 \n 당기말 자산 총액은 103조 8,715억원으로 전기말 96조 3,465억원 대비하여 7조 5,250억원 증가하였습니다.당기말 재고자산 증가로 유동자산은 전기말 대비 1조 8,263억원 증가한 28조 7,333억원을 기록하였으며 지속적인 성장을 위한 투자 집행으로 유형자산은 전기말 대비 7조 29억원 증가한 60조 2,285억원을 기록하였습니다.유형자산을 포함한 비유동자산은 전기말 대비 5조 6,987억원 증가한 75조 1,382억원을 기록하였습니다. \n 부채 \n 당기말 부채 총액은 40조 5,810억원으로 차입금 증가 등으로 전기말 34조 1,555억원 대비 6조 4,255억원 증가하였습니다. \n 자본 \n 당기말 자본 총액은 63조 2,905억원으로 당기순이익 발생 등으로 전기말 62조 1,911억원 대비 1조 995억원 증가하였습니다. \n 신규 및 중단 사업 해당사항 없습니다.\n 경영합리화 관련 해당사항 없습니다.\n 환율 변동 영향 외환위험은 미래예상거래, 인식된 자산과 부채 및 해외사업장에 대한 순투자가 기능통화 외의 통화로 표시될 때 발생합니다.당사는 영업 측면에서 매출의 대부분이 환율 변동 위험에 노출되어 있고, 생산을 위한 원부자재와 투자 관련 지출의 상당 비중이 환율 변동에 영향을 받고 있습니다.이에 당사는 외화표시 자산 및 부채에 대해 환율변동에 의한 리스크를 최소화하여 재무구조의 건전성 및 경영 안정성 제고를 목표로 환 리스크 관리에 만전을 기하고 있습니다.\n 당기말 현재 연결회사의 화폐성 외화자산 및 외화부채의 내역은 다음과 같습니다. \n (원화단위: 백만원, 외화단위: 외화 백만단위) \n 구 분 \n 자 산 \n 부 채 \n 현지통화 \n 원화환산 \n 현지통화 \n 원화환산 \n USD \n 13,372 \n 16,946,620 \n 18,956 \n 24,023,300 \n JPY \n 523 \n 4,983 \n 49,370 \n 470,581 \n CNY \n 4,656 \n 844,792 \n 1,113 \n 201,998 \n EUR \n 14 \n 19,315 \n 132 \n 177,827 \n 또한, 연결회사는 외화사채 및 차입금의 환위험을 회피하기 위하여 주석 22에서 설명하는 바와 같이 통화스왑계약 및 통화이자율스왑계약을 체결하고 있습니다. \n 당기말 현재 각 외화에 대한 기능통화의 환율이 10% 변동시, 동 환율변동이 법인세비용차감전순이익에 미치는 영향은 다음과 같습니다. \n (단위: 백만원) \n 구 분 \n 10% 상승시 \n 10% 하락시 \n USD \n (581,236) \n 581,236 \n JPY \n (46,560) \n 46,560 \n CNY \n 64,279 \n (64,279) \n EUR \n (15,851) \n 15,851 \n 당사의 환율변동위험에 대한 구체적인 내용은 'II. 사업의 내용' - '5. 위험관리 및 파생거래'를 참고하시기 바랍니다.\n 자산손상 또는 감액손실 \n 당사는 종업원급여에서 발생한 자산, 재고자산, 이연법인세자산을 제외한 모든 비금융자산에 대해서는 매 보고기간말마다 자산손상을 시사하는 징후가 있는지를 검토하며, 만약 그러한 징후가 있다면 당해 자산의 회수가능액을 추정하고 있습니다. 단, 사업결합으로 취득한 영업권 및 내용연수가 비한정인 무형자산, 아직 사용할 수 없는 무형자산에 대해서는 자산손상을 시사하는 징후와 관계없이 매년 회수가능액과 장부금액을 비교하여 손상검사를 하고 있습니다. \n 회수가능액은 개별 자산별로, 또는 개별 자산의 회수가능액을 추정할 수 없다면 그 자산이 속하는 현금창출단위별로 회수가능액을 추정하고 있으며, 회수가능액은 사용가치와 순공정가치 중 큰 금액으로 결정하고 있습니다. 당기의 계정과목별 손상차손 및 환입 인식액은 유형자산 77억원, 무형자산 1조 6,020억원 등입니다.연결회사는 당기 중 회수가능가액이 장부가액에 미달하는 개발프로젝트들에 대해 총 2,577억원의 손상차손을 인식하였습니다. 또한, 인텔NAND사업을 인수함으로써 연결범위에 편입된 SK hynix NAND Product Solutions Corp. 등의 법인들로 구성된 현금창출단위에서 미래 경제적 효익의 창출에 기여하지 못할 것으로 예상되는 자산의 장부가액 1조 3,444억원을 '기타영업외비용'으로 인식하였으며, 해당 손상 금액은 영업권 및 기타의무형자산 등에 배분되었습니다. \n 당사의 자산손상에 대한 구체적인 내용은 'Ⅲ. 재무에 관한 사항' - '3. 연결재무제표 주석'을 참고하시기 바랍니다.\n 3. 유동성 관리정책 및 현황 당기말 현재 회사가 보유 중인 현금 및 현금성 자산 합계(*) 는 6조 4,090억원으로 전기말 8조 6,725억원 대비 2조 2,636억원 감소하였습니다. 순부채는 16조 5,856억원이며, 전기말 8조 9,513억원의 순부채 대비 7조 6,343억원 증가하였습니다.(*) 현금 및 현금성 자산 합계 = 현금및현금성자산 + 단기금융상품 + 단기투자자산\n [순현금(부채) 변동내역] \n (단위: 백만원) \n 제75기 \n 제74기 \n 제73기 \n 현금및현금성자산 \n 4,977,007 \n 5,057,982 \n 2,975,989 \n 단기금융상품 및 단기투자자산 \n 1,431,985 \n 3,614,560 \n 1,972,226 \n 현금및현금성자산 합계 \n 6,408,992 \n 8,672,542 \n 4,948,215 \n 차입금(유동) \n 7,423,247 \n 2,880,763 \n 3,114,250 \n 차입금(비유동) \n 15,571,357 \n 14,743,046 \n 8,137,398 \n 차입금 합계 \n 22,994,604 \n 17,623,809 \n 11,251,648 \n 순현금(순부채) \n (16,585,612) \n (8,951,267) \n (6,303,433) \n 개별 기업의 단기적인 유동성의 건전성 수준을 가늠해 볼 수 있는 대표적인 재무비율은 유동비율과 당좌비율이 있으며, 2022년말 기준 당사의 해당 재무비율 현황은 하기와 같습니다. \n [당사 유동성 비율 추이] \n (단위 : 백만원) \n 제75기 \n 제74기 \n 제73기 \n 유동비율(= ① / ②) \n 1.4배 \n 1.8배 \n 1.8배 \n ①유동자산 \n 28,733,332 \n 26,907,075 \n 16,570,953 \n ②유동부채 \n 19,843,696 \n 14,735,395 \n 9,072,360 \n 당좌비율(= (① + ②) / ③) \n 0.6배 \n 1.1배 \n 1.1배 \n ①현금 및 현금성 자산 총액(*) \n 6,408,992 \n 8,672,542 \n 4,948,215 \n ②매출채권 \n 5,186,054 \n 8,267,111 \n 4,931,322 \n ③유동부채 \n 19,843,696 \n 14,769,356 \n 9,072,360 \n ※ 현금 및 현금성 자산 총액 = 현금및현금성자산 + 단기금융상품 + 단기투자자산 최근 3년간 당사의 유동비율은 1.4 ~ 1.8배로 적정 수준의 유동성을 유지하고 있습니다. 회사의 우수한 대외 신인도에 기반한 외부자금 조달능력 등을 감안할 때 향후 1년 기간내 회사의 유동성 위험이 발생할 가능성은 낮을 것으로 판단하고 있습니다. \n [당사 대외 신용등급 현황] \n 구분 \n 제75기말 \n 제74기말 \n 국내 \n NICE신용평가 : AA \n NICE신용평가 : AA \n 한국기업평가 : AA \n 한국기업평가 : AA \n 한국신용평가 : AA \n 한국신용평가 : AA \n 해외 \n Moody's : Baa2 \n Moody's : Baa2 \n S&P : BBB- \n S&P : BBB- \n 당사는 여유있는 유동성이 확보될 수 있도록 적절한 만기나 충분한 유동성을 제공해주는 정기예금, 수시입출금식 예금 등의 금융상품을 선택하여 잉여자금을 투자하고 있습니다. \n 2022년말 기준 회사와 종속기업이 보유하고 있는 전체 현금 및 현금성 자산 중 만기 3개월 이내의 현금 및 현금성 자산은 4조 9,770억원, 만기 1년 이내의 단기금융상품과 단기투자자산은 각각 4,156억원, 1조 164억원이며, 사용이 제한되어 있는 금융상품은 중소기업 지원을 위한 은행예금 2,225억원(상생펀드) 등 총 3,303억원입니다. (연결 재무제표 주석 '7. 사용제한 금융상품' 참조) \n 차입금 현황 \n (1) 차입금(리스부채 포함) 잔액의 변동 \n (단위 : 백만원) \n 제75기말 \n 제74기말 \n 증감* \n 금융기관차입금 \n 15,527,010 \n 9,850,058 \n 5,676,952 \n 회 사 채 \n 7,467,594 \n 7,773,751 \n (306,157) \n 리 스 부 채 \n 1,797,081 \n 1,525,762 \n 271,319 \n 기 타 \n 0 \n 0 \n - \n 계 \n 24,791,685 \n 19,149,571 \n 5,642,114 \n 가중평균차입이자율 \n 3.97% \n 1.77% \n - \n (*) 차입금의 증감에는 외화차입금에 대한 외화환산손익이 포함되어 있습니다.※ IFRS 16 개정 리스기준서 개정을 반영하여 72기부터 금융리스 운용리스 구분없이 모두 리스부채로 구분하였습니다. \n 당사는 2022년 중 주요 금융기관 등으로부터 11조 9,175억원을 신규로 조달하였으며, 회사채 및 금융기관차입금의 만기도래로 7조 1,246억원을 상환하였습니다.2022년말 당사의 연결 기준 차입금 잔액은 전기말 19조 1,496억원 대비 약 5조 6,421억원 증가하였습니다. \n (2) 만기도래 현황 \n 당사는 만기 기간별 분류에 기반한 유동성 전략 및 계획을 통하여 유동성 위험을 관리하고 있습니다. 당기말 현재 연결실체가 보유한 금융부채의 계약상 만기는 다음과 같으며, 이러한 금융부채의 조기상환의무는 없습니다. \n (단위 : 백만원) \n 1년이하 \n 1년에서 2년이하 \n 2년에서 5년이하 \n 5년초과 \n 합계 \n 금융기관차입금 \n 7,117,648 \n 2,336,123 \n 6,993,817 \n 814,108 \n 17,261,696 \n 회 사 채 \n 1,108,195 \n 2,137,426 \n 2,535,847 \n 2,357,739 \n 8,139,207 \n 계 \n 8,225,843 \n 4,473,549 \n 9,529,664 \n 3,171,847 \n 25,400,903 \n 만 기 비 중 \n 32% \n 18% \n 38% \n 12% \n 100% \n ※ 금융부채의 만기에는 차입금에 대한 이자가 포함되어 있습니다. \n (3) 조달자금과 관련된 이행조건 여부당사가 발행한 공모 사채에는 투자자 보호를 위한 재무비율 유지, 담보권 설정제한, 자산처분액 제한 등의 의무조건이 부과되어 있으며, 당사는 이와 같은 의무조건을 준수하고 있습니다. \n 리스 현황 \n 당사의 당기말 현재 리스부채와 관련된 미래 지급할 각 기간별 최소리스료의 총합계와 현재가치, 유동성 구분 내역은 다음과 같습니다. \n (단위: 백만원) \n 구 분 \n 리스료지급액 \n 1년이내 \n 293,572 \n 1년초과~5년이내 \n 843,961 \n 5년초과 \n 936,737 \n 12월 31일 현재 할인되지 않은 리스부채 \n 2,074,270 \n 12월 31일 현재 연결재무상태표에 인식된 리스부채 \n 1,797,081 \n 유동 리스부채 \n 280,873 \n 비유동 리스부채 \n 1,516,208 \n 자금 지출 관련 당사는 2020년 인텔의 Non-Volatile Memory Solutions Group의 옵테인 사업부를 제외한 NAND 사업 부문 전체를 인수하는 영업양수도 계약을 체결하였으며, 2021년 12월, NAND 사업부문 인수 1단계 절차를 완료하였습니다.인수 2단계 예상 시점인 2025년 3월에 지급할 금액은 USD 20억 수준으로 예상되며,해당 자금은 보유 현금 및 차입 등을 통해 조달할 예정입니다.※ 상기 영업양수도에 관한 상세한 내용은 2020년 10월 22일 정정공시된 '\n 주요사항보고서(영업양수결정) '를 참고하시기 바랍니다.\n 4. 부외거래 당기말 현재 당사와 관련하여 계류 중인 중요한 소송사건 및 클레임은 북미지역 내 가격 담합 집단소송과 중국 반독점법 위반조사 등이 있으며, 당사는 향후 자원의 유출가능성이 높으며 손실금액을 신뢰성 있게 추정할 수 있는 경우 동 금액을 부채로 인식하고 있습니다. 또한, 지난 2020년에 체결한 인텔의 Non-Volatile Memory Solutions Group의 옵테인 사업을 제외한 NAND 사업 전체(이하 \"인텔NAND사업\")를 인수하는 영업양수도 계약 관련하여 2차 종결이 예상되는 2025년 3월까지 잔금 USD 2,235백만을 지급할 예정입니다. 당사의 부외거래에 관한 자세한 내용은 'Ⅲ. 재무에 관한 사항' - '3. 연결재무제표 주석' 및 '5. 재무제표 주석' 내 '우발부채와 약정사항'을 참고하시기 바랍니다.\n 5. \n 그 밖에 투자의사결정에 필요한 사항 \n 중요한 회계정책 및 추정에 관한 사항 \n 연결회사는 2022년 1월 1일로 개시하는 회계기간부터 다음의 제ㆍ개정 기준서 및 해석서를 신규로 적용하였습니다.(1) 기업회계기준서 제 1116호 '리스' 개정 - 2021년 6월 30일 후에도 제공되는 코로나19 관련 임차료 할인 등코로나19의 직접적인 결과로 발생한 임차료 할인 등이 리스변경에 해당하는지 평가하지 않을 수 있도록 하는 실무적 간편법의 적용대상이 2022년 6월 30일 이전에 지급하여야 할 리스료에 영향을 미치는 리스료 감면으로 확대되었습니다. 리스이용자는 비슷한 상황에서 특성이 비슷한 계약에 실무적 간편법을 일관되게 적용해야 합니다. 해당 기준서의 개정이 연결재무제표에 미치는 중요한 영향은 없습니다.(2) 기업회계기준서 제1103호 '사업결합' 개정 - 개념체계의 인용사업결합 시 인식할 자산과 부채의 정의를 개정된 재무보고를 위한 개념체계를 참조하도록 개정되었으나, 기업회계기준서 제1037호 '충당부채, 우발부채 및 우발자산'및 해석서 제2121호 '부담금'의 적용범위에 포함되는 부채 및 우발부채에 대해서는해당 기준서를 적용하도록 예외를 추가하고, 우발자산이 취득일에 인식되지 않는다는 점을 명확히 하였습니다. 해당 기준서의 개정이 연결재무제표에 미치는 중요한 영향은 없습니다.(3) 기업회계기준서 제1016호 '유형자산' 개정 - 의도한 사용 전의 매각금액기업이 자산을 의도한 방식으로 사용하기 전에 생산된 품목의 판매에서 발생하는 수익을 생산원가와 함께 당기손익으로 인식하도록 요구하며, 유형자산의 취득원가에서차감하는 것을 금지하고 있습니다. 해당 기준서의 개정이 연결재무제표에 미치는 중요한 영향은 없습니다.(4) 기업회계기준서 제1037호 '충당부채, 우발부채 및 우발자산' 개정 - 손실부담계약: 계약이행원가손실부담계약을 식별할 때 계약이행원가의 범위를 계약 이행을 위한 증분원가와 계약 이행에 직접 관련되는 다른 원가의 배분이라는 점을 명확히 하였습니다. 해당 기준서의 개정이 연결재무제표에 미치는 중요한 영향은 없습니다.당사의 중요한 회계정책 및 추정에 관한 사항은 'III. 재무에 관한 사항' - '3. 연결재무제표 주석' - '2. 중요한 회계정책 '을 참고하시기 바랍니다. \n 한편, 당사는 전기 중 인텔 NAND사업 인수 관련 자산과 부채의 공정가치 평가를 완료할 수 없었으므로 평가액을 잠정치로 보고하였으며, 당기 중 재측정한 공정가치 결과를 반영하여 비교표시된 전기 연결재무제표를 재작성하였습니다. 이와 관련하여 구체적인 상항은 '8. 기타 재무에 관한 사항' - '가. 재무제표 재작성 등 유의사항'을 참고하시기 바랍니다. \n 환경 및 종업원 등에 관한 사항 당사의 환경관련 제재 및 이행현황 등에 관한 사항은 'XI. 그밖에 투자자 보호를 위하여 필요한 사항' - '3. 제재 등과 관련된 사항'을 참고하시기 바랍니다.종업원과 관련하여 주요 핵심인력 이동 등 회사 인력의 중요한 변동은 없었으며, 종업원 현황 등 종업원과 관련된 구체적인 사항은 'Ⅷ. 임원 및 직원 등에 관한 사항'을 참조하시기 바랍니다.\n 법규상의 규제에 관한 사항 당사가 영위하는 사업과 관련된 법규상 주요 규제내용에 관한 사항은 'Ⅱ. 사업의 내용' - '7. 기타 참고사항' - '마. 정부나 지방자치단체의 법률 규정 등에 의한 규제사항'을 참고하시기 바랍니다. \n 파생상품 및 위험관리정책에 관한 사항 당사의 주요 파생상품 및 위험관리정책은 'II. 사업의 내용' - '5. 위험관리 및 파생거래' 및 'Ⅲ. 재무에 관한 사항' - '3. 연결재무제표 주석'을 참고하시기 바랍니다.\n V."
    }
  }
}